Workbook

Sheet UnitTenant Mix
A1: Owner | B1: Name | C1: Space | D1: Width | E1: Length | F1: Height | G1: Rate (Cost Price) | H1: Web Rate (not there on app right now) | I1: Space Size [width * length] | J1: Space Category | K1: Door Width | L1: Door Height display in application as w*h when available in database) | M1: Amenities | N1: Sq. Ft. | O1: Floor (application does not allow non numeric values, but can be entered through backend) | P1: First Name | Q1: Last Name | R1: Middle Name | S1: Account Code | T1: Address | U1: City | V1: State | W1: ZIP | X1: Country | Y1: email | Z1: Primary Phone | AA1: Secondary Phone | AB1: Tertiary Phone | AC1: Access Code | AD1: DOB | AE1: Active Military | AF1: DL Id | AG1: DL State | AH1: DL City | AI1: DL Exp Date | AJ1: Rent | AK1: Last Rent Change Date | AL1: Move In Date | AM1: Move Out Date | AN1: Paid Date | AO1: Bill Day | AP1: Paid Through Date | AQ1: Alt First Name | AR1: Alt Last Name | AS1: Alt Middle Name | AT1: Alt Address | AU1: Alt City | AV1: Alt State | AW1: Alt ZIP | AX1: Alt Email | AY1: Alt Home Phone | AZ1: Alt Work Phone | BA1: Alt Cell Phone | BB1: Security Deposit (prods defined and on MSR but not on application yet) | BC1: Security Deposit Balance | BD1: Rent Balance | BE1: Fees Balance | BF1: Protection/Insurance Balance | BG1: Merchandise Balance | BH1: Late Fees Balance | BI1: Lien Fees Balance | BJ1: Tax Balance | BK1: Prepaid Rent | BL1: Prepaid Additional Rent/ Premium | BM1: Prepaid Tax | BN1: Protection/Insurance Provider | BO1: Protection/Insurance Coverage | BP1: Additional Rent/Premium | BQ1: Delinquency Status | BR1: Lien Status | BS1: Lien Posted Date (when lien was initiated) | BT1: Promotion | BU1: Promotion Type | BV1: Promotion Value | BW1: Promotion Start | BX1: Promotion Length | BY1: Discount | BZ1: Discount Type | CA1: Discount Value
A2: [Storage Provider Name] | B2: [Facility/Property Name] | C2: [Space Number] | D2: [Width] | E2: [Length] | F2: [Height] | G2: [Price] | H2: [Price Displayed on Web] | I2: [5 x 10, 5 x 5] | J2: [Interior, Drive Up, Climate Controled] | K2: [Width] | L2: [Height] | M2: [Cabnits, Shelves, Alarm, Light etc.] | O2: [Ground, 1st, 1 etc.] | P2: [Tenant First Name] | Q2: [Tenant Last Name] | R2: [Tenant Middle Name] | S2: [For Unique Tenant Identification] | AC2: [Gate Access Code] | AD2: [Date of Birth] | AE2: [True/False] | AF2: [Driving License ID] | AG2: [Driving License State] | AH2: [Driving License City] | AI2: [Driving License Expiry Date] | AJ2: [Rent Amount] | BQ2: [True/False] | BT2: [Promotion Name] | BU2: [Promotion Fixed/Percentage/Dollar] | BV2: [Amount] | BW2: [Promotion Start Date] | BX2: [Promotion Length Months] | BY2: [Discount Name] | BZ2: [Discount Fixed/Percentage/Dollar] | CA2: [Amount]
A3: Do not fill out | B3: Do not fill out | C3: Numeric or alpha numeric (i.e. 101, A101, 101C) | D3: ex. 10 or 10.5 | E3: ex. 10 or 10.5 | F3: ex. 10 or 10.5 (for parking spaces height can be 0) | G3: Sell Rate - Can include decimals | H3: We currently do not have separate rates for Website. This field would be a copy of Column G - Rate (or leave blank) until this functionality is implemented on HB | I3: In the format [width] x [length], can include decimals | N3: This should be a calculated product of width * length | S3: Make sure the First name Last name, Email, Phone Number, Account Code and Addresses (both Primary and Alternate) match for the tenants with same First name last Name and Email Addresses | T3: Includes both Address line 1 and 2. Ex: 4920 Campus Dr, Suite B | V3: This should be in "CA" format instead of "California". Should use address verification migration package to validate this | Z3: No formatting, entered as 1234567980 | AA3: No formatting, entered as 1234567980 | AB3: No formatting, entered as 1234567980 | AD3: Format mm/dd/yyyy | AE3: FALSE | AG3: Format should be "CA" instead of "California" | AI3: Format mm/yyyy | AK3: Format mm/dd/yyyy | AL3: Format mm/dd/yyyy | AM3: Format mm/dd/yyyy | AN3: Format mm/dd/yyyy | AO3: number 1-30/31, when the tenant is billed | AP3: Format mm/dd/yyyy | BD3: Required if a tenant is Past Due | BE3: Required if a tenant is Past Due and has fees other than Late Fees | BF3: Required if a tenant has past due for Coverage | BG3: Required if a tenant has past due for Merchandise | BH3: Required if a tenant is Past Due and has Late Fee | BI3: Required if a tenant is Past Due and has Lien Fee | BJ3: Required if a tenant is Past Due and has Tax Balance | BK3: Required if a tenant has Prepaid Rent | BL3: Required if a tenant has Prepaid Coverage | BM3: Required if a tenant has Prepaid Tax | BN3: Required if a tenant has a Coverage | BO3: Required if a tenant has a Coverage | BP3: Required if a tenant has a Coverage | BQ3: Do not fill out, will be based on outstanding balances | BR3: Do not fill out, will be based on paid thru date | BS3: Do not fill out | BY3: NOTE: Discounts are applied to the lifetime of the tenants (no end date)
C4: no special charaters | D4: number between 0 and 100 | E4: number between 0 and 101 | F4: number between 0 and 102 | G4: Only number AND no special charaters | H4: hidden | I4: auto | J4: no validation | K4: only numbers no special charaters | L4: only numbers no special charaters | M4: hide | O4: no special charaters | P4: no validation | Q4: no validation | R4: no validation | S4: protect range | T4: no validtion | U4: no special charaters besides dash | V4: only text | W4: only number and dash no special charaters | X4: default USA using if stament | Y4: is valid email | Z4: 4175228858 | AA4: 417-522-8858234 | AC4: no special charaters no letter | AD4: is. a valid date reject input | AE4: formula for only true or false | AF4: no special charaters | AJ4: only numbers from 0 to 10,000
AE5: TRUE
AE6: TRUE
AE7: FALSE
AE8: FALSE
M9: ` | AE9: FALSE
AE10: FALSE
AE11: FALSE
AE12: FALSE
AE13: FALSE
AE14: FALSE
AE15: FALSE
AE16: FALSE
AE17: FALSE
AE18: FALSE
AE19: FALSE
AE20: FALSE
AE21: FALSE
... AE1000: FALSE

Sheet Instructions
A1: Instructions:
B2: When pasting please paste with values. (Windows: Ctrl+Shift+V or Mac: Command+Shift+V)
A4: Tabs | B4: Instructions
A5: Space Mix | B5: All yellow columns are required. Grey columns are auto filled. White columns are optional. | G5: Required | H5: Not Required | I5: Auto Filled
A6: Tenant Info | B6: Yellow columns will prepopulate with the data that is filled in on the space mix tab. Green columns are required. White Coulmns are optional. | G6: Pre-populated | H6: Required | I6: Not Required | J6: Auto Filled
A7: Tenant Payment Info | B7: Yellow and green columns will prepopulate from Space Mix tab and Tenant Info tab. Blue columns are required. White columns are optional | G7: Pre-populated | H7: Pre-populated | I7: Required | J7: Not Required | K7: Auto Filled | L7: Required
A8: Promotions/Discounts | B8: This tab is not required unless a tenant has a recurring discount or promotion. | G8: Pre-populated | H8: Pre-populated | I8: Required
A9: Final Sheet (Ony View) | B9: All data from each tab will fill in and allows you to view all data entry on one sheet. This is a protected sheet, so you will only be able to view but not edit. If you want to edit something please go to the respective tab and make the change.
A10: Description Format Info | B10: You can find descriptions and format of each column of each tab of the spreadsheet
A11: MIG Team Final Sheet | B11: Pleas don't fill out. For our internal team only

Sheet Description Format Info
A1: Name of Column | B1: Description | C1: Format | D1: Required/Optional | E1: Notes
A2: Spaces
A3: Space | B3: This is the identification number assigned to the space. It can consist of either a number or a combination of letters and numbers. | C3: 101 or A-101 | D3: Required
A4: Width | B4: The width of the space refers to the measurement from one side to the other. It can be a whole number or a number with decimal points. | C4: 10 or 10.5 | D4: Required
A5: Length | B5: The length of the space is the measurement from one end to the other. Like the width, it can also be a whole number or a number with decimal points. | C5: 10 or 10.5 | D5: Required
A6: Height | B6: The height of the space represents the vertical measurement. It can be a whole number or a number with decimal points. For parking spaces, the height can be entered as 0, indicating a flat surface. | C6: 10 or 10.5 | D6: Required
A7: Rate (Cost Price) | B7: The Rate or Cost Price of the space is the price at which the space is sold to customers. This value can be represented as either a whole number or a number with decimal points, depending on the specific pricing of the space. It reflects the monetary amount that customers need to pay to acquire the space. | C7: 100 or 48.5 | D7: Required
A8: Web Rate (not there on app right now) | B8: The Web Rate refers to the price at which the space is advertised on the website. This value can be expressed as either a whole number or a number with decimal points, depending on the specific pricing. It is the price that customers will see and consider when making a decision to book the space through the website. NOTE: For Hummingbird currently the Rate and Web Rate would be the same as we do not have differential pricing. | C8: 100 or 48.5 | D8: Required
A9: Space Size | B9: The size of the space expressed in [width] * [length] format. This is a calculated value. | C9: 10 x 10 or 10.5 x 10.5 | D9: Calculated Value
A10: Space Category | B10: The category of the space. | C10: Interior | D10: Required
A11: Door Width | B11: The width of the door. This can be a number or a decimal. | C11: 8 or 8.75 | D11: Optional
A12: Door Height | B12: The height of the door. This can be a number or a decimal. | C12: 8 or 8.75 | D12: Optional
A13: Amenities | B13: The amenities of the space. Amenities are entered as comma separated. This is currently are now handled by Rate Management | C13: Tall Door, Lights in Unit | D13: Do not enter
A14: Sq. Ft. | B14: The square footage of the space is a calculated value obtained by multiplying the width and length of the space. This value represents the total area covered by the space in square feet. | C14: 100 or 110.25 | D14: Calculated Value
A15: Floor | B15: The floor indicates the specific level or storey where the space is situated within a building or a facility. For example, if the space is located on the ground level, it would be indicated as "0." If it is on the first level above the ground floor, it would be labeled as "1" and so on. NOTE: Please indicate all Floors in a numeric value | C15: 1 or 0 | D15: Required | E15: This would be a requirement when Property Map feature is in production
A17: Tenants
A18: First Name | B18: The first name of the tenant occupying that space. | C18: Joe | D18: Required | E18: Ensure that the First Name, Last Name, Email, Phone Number, Account Code, and Addresses (both Primary and Alternate) are consistent for tenants who have multiple spaces linked to their account. This means verifying and ensuring that all their details are the same across all the spaces they occupy. By doing this, we can avoid any discrepancies and maintain accurate and uniform information for tenants who have multiple spaces under their account. This helps in organizing tenant data and streamlining administrative processes for efficient tenant management.
A19: Last Name | B19: The last name of the tenant occupying that space. | C19: Doe | D19: Required
A20: Middle Name | B20: The middle name of the tenant occupying that space | C20: Yoda | D20: Optional
A21: Account Code | B21: The Account Code is primarily used when there are multiple spaces associated with one tenant. In such cases, the tenant assigns the same number next to each of those spaces to create unique identifiers. For instance, if Tenant Yoda has both Space 101 and Space 102, they would use the Account Code "1" for both spaces. Similarly, if Tenant Darth has Space 103, they would use the Account Code "2" for that particular space. By using Account Codes, it becomes easier to link and manage multiple spaces that belong to the same tenant. This system ensures clear identification and organization, allowing for efficient record-keeping and invoicing processes. It helps property managers or administrators easily track and associate specific spaces with their corresponding tenants, streamlining administrative tasks and facilitating accurate billing and documentation. Space Account Code 101 1 102 1 103 2 | C21: 1 | D21: Auto Generated based on gate access code
A22: Address | B22: The address of the tenant occupying that space. This field includes both Address 1 and Address 2 of the tenant. | C22: 4920 Campus Dr, Suite B | D22: Required
A23: City | B23: The city in which the tenant is located at. | C23: Irvine | D23: Required
A24: State | B24: The abbreviation of the state in which the tenant is located at. | C24: CA | D24: Required
A25: ZIP | B25: The zipcode of the address where the tenant is located at. | C25: 90007 or HAP123 | D25: Required
A26: Country | B26: The country where the tenant is located at. We currently only support USA. | C26: USA | D26: Required
A27: Email | B27: The email address of the tenant. | C27: abc@gmail.com | D27: Required
A28: Cell Phone | B28: The cell phone number of the tenant. Ensure to enter just the phone number without the country code. For example, if your phone number is +1 (213) 111-0000, the phone number field should be filled in as 2131110000 (no formatting needed). | C28: 2131110000 | D28: Required | E28: At least one phone number is needed which would then become the Primary Phone Number
A29: Home Phone | B29: The home phone number of the tenant. Ensure to enter just the phone number without the country code. For example, if your phone number is +1 (213) 111-0000, the phone number field should be filled in as 2131110000 (no formatting needed). | C29: 2131110000 | D29: Optional
A30: Work Phone | B30: The work phone number of the tenant. Ensure to enter just the phone number without the country code. For example, if your phone number is +1 (213) 111-0000, the phone number field should be filled in as 2131110000 (no formatting needed). | C30: 2131110000 | D30: Optional
A31: Access Code | B31: The Access Code is a unique numeric code assigned to each tenant for secure access purposes. It can be either a custom code or the last 5 digits of the tenant's phone number. Access codes are always numeric and can range from 1 to 9 digits in length. This code is used to authenticate the tenant's identity and grant them access to specific areas or facilities. | C31: 12345 | D31: Required | E31: can use the last 4 digits of their phone number as access code
A32: DOB | B32: The date of birth of the tenant. This should be in the format MM/DD/YYYY. | C32: 09/11/2015 | D32: Optional
A33: Active Military | B33: If the tenant is in active military, enter Yes. Else enter No. | C33: Yes or No | D33: Optional
A34: DL Id | B34: The Driver's License number of the tenant. | C34: DL12345 | D34: Optional
A35: DL State | B35: The abbreviated state in which the Driver's License was issued for the tenant. | C35: CA | D35: Optional
A36: DL City | B36: The city in which the Driver's License was issued for the tenant. | C36: Irvine | D36: Optional
A37: DL Exp Date | B37: The expiration date of the Driver's License | C37: 08/2020 | D37: Optional
A38: Rent | B38: The rent the tenant is currently being charged for the space. | C38: 100 or 100.05 | D38: Required
A39: Last Rent Change Date | B39: The date when the last rent change was done | C39: 01/10/2020 | D39: Optional | E39: NOTE: If the operator does not provide this information, the last rent change would be calculated from their move in date on HB
A40: Move In Date | B40: The date the tenant moved into the space. This should be in the format MM/DD/YYYY. | C40: 01/01/2020 | D40: Required
A41: Move Out Date | B41: This should only be entered if an existing tenant is scheduled to move out. This should be in the format MM/DD/YYYY. | C41: 01/10/2020 | D41: Optional
A42: Bill Day | B42: The day the tenant should be billed. This would be 1 for FOM properties, indicating Day 1 | C42: 1 | D42: Required
A43: Paid Date | B43: The date the last payment was made. This should be in the format MM/DD/YYYY. | C43: 01/08/2020 | D43: Required | E43: 1st of that month if FOM and anniversary should be the month prior
A44: Paid Through Date | B44: The Paid Through Date refers to the date until which the tenant has made payments. This date is in the format MM/DD/YYYY and is calculated based on the last date for which the last invoice was paid in full. For instance, if the invoice for August 1st was paid in full, then the Paid Through Date would be 08/31/2022 for properties with a monthly billing cycle. Note: In cases of Pre-Payment, the Paid Through Date remains the end of the current month during data migration, regardless of the tenant's actual payment schedule. For example, if a tenant has paid until the end of August, and the data migration is done in the month of May, the Paid Through Date for this tenant would be 05/30/2022 instead of 08/31/2022. The data team will use the values under the Prepaid Rent field to calculate the Prepaid invoices accurately. This ensures that the Paid Through Date is appropriately aligned with the migration timeline, maintaining data consistency and accuracy during the migration process.NOTE: For Pre-Payment, the Paid Through Date should still be the end of the curernt month of migrating data. For example, if a tenant has paid till end of August, and the data is being migrated in the month of May, the Paid Through Date for this tenant would be 05/30/2022 instead of 08/31/2022. The data team would use the values under the Prepaid Rent field to calculate the Prepaid invoices. | C44: 08/31/2020 | D44: Required | E44: Make sure that if a tenant a tenant is delinquent, the Paid Through Date and rent balance is appropriately filled in. For example, if a tenant for the month of April has a rent of $30 and a past due of $35, then the Rent Balance = $35 and the Paid Through Date would be 03/31/2022 (They owe for April and are paid through March).
A45: Alt First Name | B45: The first name of the alternate contact of the tenant occupying that space. | C45: Luke | D45: Optional
A46: Alt Last Name | B46: The last name of the alternate contact of the tenant occupying that space. | C46: Skywalker | D46: Optional
A47: Alt Middle Name | B47: The middle name of the alternate contact of the tenant occupying that space | C47: Chewbacca | D47: Optional
A48: Alt Address | B48: The address of the alternate contact of the tenant occupying that space. This field includes both Address 1 and Address 2 of the tenant. | C48: 4920 Campus Dr, Suite B | D48: Optional
A49: Alt City | B49: The city in which the alternate contact of the tenant is located at. | C49: Irvine | D49: Optional
A50: Alt State | B50: The abbreviation of the state in which the alternate contact of the tenant is located at. | C50: CA | D50: Optional
A51: Alt ZIP | B51: The zipcode of the address where the alternate contact of the tenant is located at. | C51: 90007 or HAP123 | D51: Optional
A52: Alt Email | B52: The email address of the alternate contact of the tenant. | C52: abc@gmail.com | D52: Optional
A53: Alt Home Phone | B53: The cell phone number of the alternate contact of the tenant. Ensure to enter just the phone number without the country code. For example, if your phone number is +1 (213) 111-0000, the phone number field should be filled in as 2131110000 (no formatting needed). | C53: 2131110000 | D53: Optional
A54: Alt Work Phone | B54: The home phone number of the alternate contact of the tenant. Ensure to enter just the phone number without the country code. For example, if your phone number is +1 (213) 111-0000, the phone number field should be filled in as 2131110000 (no formatting needed). | C54: 2131110000 | D54: Optional
A55: Alt Cell Phone | B55: The work phone number of the alternate contact of the tenant. Ensure to enter just the phone number without the country code. For example, if your phone number is +1 (213) 111-0000, the phone number field should be filled in as 2131110000 (no formatting needed). | C55: 2131110000 | D55: Optional
A56: Security Deposit | B56: The security deposit that is paid by the tenant and is a number field. | C56: 105 | D56: Optional
A57: Security Deposit Balance | B57: The security deposit balance that is owed by the tenant and is a number field. | C57: 100 or 110.25 | D57: Optional
A58: Rent Balance | B58: This is a number field that shows the rent owed. Eg: $80. This is not a required field. If the tenant has a rent of $50, and the tenant has not paid the last generated invoice which makes him due of $50, then the rent balance would be 50. If the tenant owes two month’s rent of $50, then their rent balance would be 100. | C58: 100 or 110.25 | D58: Required if a tenant is Past Due
A59: Fees Balance | B59: The fees that the tenant owes excluding late fees and lien fees. This is a number field and the number is expressed with a $ sign. Eg: If a tenant had the following fees: 1. Admin fees of $20 2. Late fees of $10 3. Service fee of $50 Then the fee balance would be $70 (admin fee + service fee). | C59: 100 or 110.25 | D59: Required if a tenant is Past Due and has fees other than Late Fees
A60: Protection/Insurance Balance | B60: The Protection Plan or Insurance balance that the tenant the tenant owes. If the tenant has a protection plan for $9 per month but had paid $7, then the protection/insurance balance would be 2 | C60: 2 or 2.75 | D60: Required if a tenant has past due for Coverage
A61: Merchandise Balance | B61: The merchandise amount the tenant had last purchased and had not paid for. This is a number field and the number and is expressed with a $ sign. Eg: 80. | C61: 100 or 110.25 | D61: Required if a tenant has past due for Merchandise
A62: Late Fees Balance | B62: If the tenant owes any late fees, then they would have to fill in a $ amount on this field. This would generate a separate invoice. Eg: if a tenant has an admin fees of $20, a late fees of $10 and a service fee of $50, then the late fees balance would be 10. | C62: 100 or 110.25 | D62: Required if a tenant is Past Due and has Late Fee
A63: Lien Fees Balance | B63: If the tenant owes any lien fees, then they would have to fill in a $ amount on this field. This would generate a separate invoice. Eg: if a tenant has an admin fees of $20, a late fees of $10 and a lien fee of $50, then the lien fees balance would be 50. | C63: 100 or 110.25 | D63: Required if a tenant is Past Due and has Lien Fee
A64: Tax Balance | B64: If the tenant owes any tax on their latest invoice, enter in the tax as a $ amount. This can be a whole number or a decimal. | C64: 100 or 110.25 | D64: Required if a tenant is Past Due and has Tax Balance
A65: Prepaid Rent | B65: If the tenant has prepaid, enter the prepaid rent amount. If the tenant has a rent of $50 and prepaid two months, then the prepaid rent would be 100 | C65: 100 or 110.25 | D65: Required if a tenant has Prepaid Rent
A66: Prepaid Premium | B66: If a tenant has prepaid any additional premium, then it would display in here | C66: 2 or 2.75 | D66: Required if a tenant has Prepaid Coverage
A67: Prepaid Tax | B67: If a tenant owes a tax of $8 for my prepaid rent of $50, then the prepaid tax would be 8. | C67: 3 or 1.01 | D67: Required if a tenant has Prepaid Tax
A68: Protection/Insurance Provider | B68: The name of the Insurance or Protection provider | C68: Storelocal Protection | D68: Required if a tenant has a Coverage
... A70: Additional Rent/Premium | B70: The premium that the tenant owes for the chosen coverage | C70: 9 | D70: Required if a tenant has a Coverage
A71: Delinquency Status
A72: Lien Status
A73: Lien Posted Date (when lien was initiated)
A74: Commanding Officer First Name | B74: The first name of the Commanding Officer | C74: Joe | D74: Required if entering in Military Information
A75: Commanding Officer Last Name | B75: The last name of the Commanding Officer | C75: Doe | D75: Required if entering in Military Information
A76: Commanding Officer Phone | B76: The phone number of the Commanding Officer | C76: 2131110000 | D76: Required if entering in Military Information
A77: Commanding Officer Email | B77: The email of the Commanding Officer | C77: abc@gmail.com | D77: Optional
A78: Rank | B78: The rank of the Commanding Officer | C78: Dropdown | D78: Optional
A79: Military Serial Number | B79: The military serial number | D79: Required if entering in Military Information
A80: Military Email | B80: The military email address | D80: Optional
A81: Service Member DOB | B81: The date of birth of the service member | D81: Optional
A82: Expiration Term of Service | B82: The militray expiration term of service | D82: Optional
A83: Military Branch | B83: The militray branch of the tenant/service member | D83: Required if entering in Military Information
A84: Military Unit Name | B84: The name of the military unit | D84: Optional
A85: Military Unit Phone | B85: The phone number in the military unit | D85: Optional
A86: Military Unit Address 1 | B86: The address 1 of the military unit | D86: Optional
A87: Military Unit Address 2 | B87: The address 2 of the military unit | D87: Optional
A88: Military City | B88: The city of the military unit | D88: Optional
A89: Military Unit State | B89: The state of the military unit | D89: Optional
A90: Military Unit Zipcode | B90: The zipcode of the military unit | D90: Optional
... A99: Lien Holder Zipcode | B99: The zipcode of the Lien Holder | D99: Optional

Sheet Space mix
A1: Space | C1: Space Type | D1: Width | E1: Length | F1: Height | G1: Rate | H1: Space Category | I1: Floor | J1: Door Width | K1: Door Height | L1: Space Size | M1: Sq. Ft.
A2: 101 or A-101 | B2: Occupied or Vacant | C2: Storage or Parking | D2: 10 or 10.5 | E2: 10 or 10.5 | F2: 10 or 10.5 | G2: 100 or 48.5 | H2: Drive Up or Climate Controled | I2: 0, 1st, 1 | J2: 8 or 8.75 | K2: 8 or 8.75 | L2: [5 x 10]
L3: ="["&D3&" X "&E3&"]" | M3: =D3*E3

Sheet Tenant Info
A1: ='Space mix'!A1 -> Space | B1: ='Space mix'!B1 | C1: First Name | D1: Last Name | E1: Middle Name | F1: Rent | G1: Move In Date | H1: Active Military | I1: Account Code | J1: Address | K1: City | L1: State | M1: ZIP | N1: Country | O1: Email | P1: Cell Phone | Q1: Home Phone | R1: Work Phone | S1: Access Code | T1: DL Id | U1: DL State | V1: DL City | W1: DL Exp Date | X1: Alt First Name | Y1: Alt Last Name | Z1: Alt Middle Name | AA1: Alt Address | AB1: Alt City | AC1: Alt State | AD1: Alt ZIP | AE1: Alt Email | AF1: Alt Home Phone | AG1: Alt Work Phone | AH1: Alt Cell Phone
A2: ='Space mix'!A2 -> 101 or A-101 | B2: ='Space mix'!B2 -> Occupied or Vacant | C2: Joe | D2: Doe | E2: Yoda | F2: 100 or 100.05 | G2: MM/DD/YYYY | H2: [True/False] | I2: [For Unique Tenant Identification] | J2: 4920 Campus Dr, Suite B | K2: Newport Beach | L2: CA | M2: 90007 or HAP123 | N2: USA | O2: abc@gmail.com | P2: 2131110000 (no formatting) | Q2: 2131110001 (no formatting) | R2: 2131110002 (no formatting) | S2: 12345 (btwn 1-9 digits) | T2: DL12345 | U2: CA | V2: Newport Beach | W2: MM/YYYY | X2: Luke | Y2: Skywalker | Z2: Chewbacca | AA2: 4920 Campus Dr, Suite B | AB2: Irvine | AC2: CA | AD2: 90007 or HAP123 | AE2: abc@gmail.com | AF2: 2131110000 (no formatting) | AG2: 2131110000 (no formatting) | AH2: 2131110000 (no formatting)
A3: ='Space mix'!A3 | B3: ='Space mix'!B3 | F3: =XLOOKUP(A3,'Space mix'!$A$3:$A$832,'Space mix'!$G$3:$G$832)
A4: ='Space mix'!A4 | B4: ='Space mix'!B4 | F4: =XLOOKUP(A4,'Space mix'!$A$3:$A$832,'Space mix'!$G$3:$G$832)
A5: ='Space mix'!A5 | B5: ='Space mix'!B5 | F5: =XLOOKUP(A5,'Space mix'!$A$3:$A$832,'Space mix'!$G$3:$G$832)
A6: ='Space mix'!A6 | B6: ='Space mix'!B6 | F6: =XLOOKUP(A6,'Space mix'!$A$3:$A$832,'Space mix'!$G$3:$G$832)
A7: ='Space mix'!A7 | B7: ='Space mix'!B7 | F7: =XLOOKUP(A7,'Space mix'!$A$3:$A$832,'Space mix'!$G$3:$G$832)
A8: ='Space mix'!A8 | B8: ='Space mix'!B8 | F8: =XLOOKUP(A8,'Space mix'!$A$3:$A$832,'Space mix'!$G$3:$G$832)
A9: ='Space mix'!A9 | B9: ='Space mix'!B9 | F9: =XLOOKUP(A9,'Space mix'!$A$3:$A$832,'Space mix'!$G$3:$G$832)
A10: ='Space mix'!A10 | B10: ='Space mix'!B10 | F10: =XLOOKUP(A10,'Space mix'!$A$3:$A$832,'Space mix'!$G$3:$G$832)
A11: ='Space mix'!A11 | B11: ='Space mix'!B11 | F11: =XLOOKUP(A11,'Space mix'!$A$3:$A$832,'Space mix'!$G$3:$G$832)
A12: ='Space mix'!A12 | B12: ='Space mix'!B12 | F12: =XLOOKUP(A12,'Space mix'!$A$3:$A$832,'Space mix'!$G$3:$G$832)
A13: ='Space mix'!A13 | B13: ='Space mix'!B13 | F13: =XLOOKUP(A13,'Space mix'!$A$3:$A$832,'Space mix'!$G$3:$G$832)
A14: ='Space mix'!A14 | B14: ='Space mix'!B14 | F14: =XLOOKUP(A14,'Space mix'!$A$3:$A$832,'Space mix'!$G$3:$G$832)
... A832: ='Space mix'!A832 | B832: ='Space mix'!B832 | F832: =XLOOKUP(A832,'Space mix'!$A$3:$A$832,'Space mix'!$G$3:$G$832)
A833: ='Space mix'!A833 | B833: ='Space mix'!B833 | I833: =S833
A834: ='Space mix'!A834 | B834: ='Space mix'!B834
A835: ='Space mix'!A835 | B835: ='Space mix'!B835
A836: ='Space mix'!A836 | B836: ='Space mix'!B836
A837: ='Space mix'!A837 | B837: ='Space mix'!B837
A838: ='Space mix'!A838 | B838: ='Space mix'!B838
A839: ='Space mix'!A839 | B839: ='Space mix'!B839
A840: ='Space mix'!A840 | B840: ='Space mix'!B840
A841: ='Space mix'!A841 | B841: ='Space mix'!B841
A842: ='Space mix'!A842 | B842: ='Space mix'!B842
A843: ='Space mix'!A843 | B843: ='Space mix'!B843
A844: ='Space mix'!A844 | B844: ='Space mix'!B844
A845: ='Space mix'!A845 | B845: ='Space mix'!B845
... A1999: ='Space mix'!A1999 | B1999: ='Space mix'!B1999

Sheet Tenants Lien Holder Information
A1: ='Space mix'!A1 -> Space | B1: ='Space mix'!B1 | C1: ='Tenant Info'!C1 -> First Name | D1: ='Tenant Info'!D1 -> Last Name | E1: Lien Holder First Name | F1: Lien Holder Last Name | G1: Lien Holder Email | H1: Lien Holder Phone | I1: Lien Holder Address 1 | J1: Lien Holder Address 2 | K1: Lien Holder City | L1: Lien Holder State | M1: Lien Holder Zipcode
A2: ='Space mix'!A2 -> 101 or A-101 | B2: ='Space mix'!B2 -> Occupied or Vacant | C2: ='Tenant Info'!C2 -> Joe | D2: ='Tenant Info'!D2 -> Doe | E2: Anna | F2: Doe | G2: anna@email.com | H2: 2131110001 (no formatting) | I2: 4920 Campus Dr. | J2: Suite B | K2: Newport Beach | L2: CA | M2: 92612
A3: ='Space mix'!A3 | B3: ='Space mix'!B3 | C3: ='Tenant Info'!C3 | D3: ='Tenant Info'!D3
A4: ='Space mix'!A4 | B4: ='Space mix'!B4 | C4: ='Tenant Info'!C4 | D4: ='Tenant Info'!D4
A5: ='Space mix'!A5 | B5: ='Space mix'!B5 | C5: ='Tenant Info'!C5 | D5: ='Tenant Info'!D5
A6: ='Space mix'!A6 | B6: ='Space mix'!B6 | C6: ='Tenant Info'!C6 | D6: ='Tenant Info'!D6
A7: ='Space mix'!A7 | B7: ='Space mix'!B7 | C7: ='Tenant Info'!C7 | D7: ='Tenant Info'!D7
A8: ='Space mix'!A8 | B8: ='Space mix'!B8 | C8: ='Tenant Info'!C8 | D8: ='Tenant Info'!D8
A9: ='Space mix'!A9 | B9: ='Space mix'!B9 | C9: ='Tenant Info'!C9 | D9: ='Tenant Info'!D9
A10: ='Space mix'!A10 | B10: ='Space mix'!B10 | C10: ='Tenant Info'!C10 | D10: ='Tenant Info'!D10
A11: ='Space mix'!A11 | B11: ='Space mix'!B11 | C11: ='Tenant Info'!C11 | D11: ='Tenant Info'!D11
A12: ='Space mix'!A12 | B12: ='Space mix'!B12 | C12: ='Tenant Info'!C12 | D12: ='Tenant Info'!D12
A13: ='Space mix'!A13 | B13: ='Space mix'!B13 | C13: ='Tenant Info'!C13 | D13: ='Tenant Info'!D13
A14: ='Space mix'!A14 | B14: ='Space mix'!B14 | C14: ='Tenant Info'!C14 | D14: ='Tenant Info'!D14
... A1000: ='Space mix'!A1000 | B1000: ='Space mix'!B1000 | C1000: ='Tenant Info'!C1000 | D1000: ='Tenant Info'!D1000

Sheet Tenants Military Information
A1: ='Tenant Info'!A1 -> Space | B1: ='Space mix'!B1 | C1: ='Tenant Info'!H1 -> Active Military | D1: ='Tenant Info'!C1 -> First Name | E1: ='Tenant Info'!D1 -> Last Name | F1: Commanding Officer First Name | G1: Commanding Officer Last Name | H1: Commanding Officer Phone | I1: Commanding Officer Email | J1: Rank | K1: Military Serial Number | L1: Military Email | M1: Service Member DOB | N1: Expiration Term of Service | O1: Military Branch | P1: Military Unit Name | Q1: Military Unit Phone | R1: Military Unit Address 1 | S1: Military Unit Address 2 | T1: Military City | U1: Military Unit State | V1: Military Unit Zipcode
A2: ='Tenant Info'!A2 -> 101 or A-101 | B2: ='Space mix'!B2 -> Occupied or Vacant | C2: ='Tenant Info'!H2 -> [True/False] | D2: ='Tenant Info'!C2 -> Joe | E2: ='Tenant Info'!D2 -> Doe | F2: Joe | G2: Doe | H2: Doe | I2: joedoe@email.com | J2: Captain | K2: X111222 | L2: joe@usmilitary.com | M2: MM/DD/YYYY | N2: MM/DD/YYYY | O2: Navy | P2: Test | Q2: 2131110000 (no formatting) | R2: 4920 Campus Dr | S2: Suite B | T2: Irvine | U2: CA | V2: 92612
A3: ='Tenant Info'!A3 | B3: ='Space mix'!B3 | C3: ='Tenant Info'!H3 | D3: ='Tenant Info'!C3 | E3: ='Tenant Info'!D3
A4: ='Tenant Info'!A4 | B4: ='Space mix'!B4 | C4: ='Tenant Info'!H4 | D4: ='Tenant Info'!C4 | E4: ='Tenant Info'!D4
A5: ='Tenant Info'!A5 | B5: ='Space mix'!B5 | C5: ='Tenant Info'!H5 | D5: ='Tenant Info'!C5 | E5: ='Tenant Info'!D5
A6: ='Tenant Info'!A6 | B6: ='Space mix'!B6 | C6: ='Tenant Info'!H6 | D6: ='Tenant Info'!C6 | E6: ='Tenant Info'!D6
A7: ='Tenant Info'!A7 | B7: ='Space mix'!B7 | C7: ='Tenant Info'!H7 | D7: ='Tenant Info'!C7 | E7: ='Tenant Info'!D7
A8: ='Tenant Info'!A8 | B8: ='Space mix'!B8 | C8: ='Tenant Info'!H8 | D8: ='Tenant Info'!C8 | E8: ='Tenant Info'!D8
A9: ='Tenant Info'!A9 | B9: ='Space mix'!B9 | C9: ='Tenant Info'!H9 | D9: ='Tenant Info'!C9 | E9: ='Tenant Info'!D9
A10: ='Tenant Info'!A10 | B10: ='Space mix'!B10 | C10: ='Tenant Info'!H10 | D10: ='Tenant Info'!C10 | E10: ='Tenant Info'!D10
A11: ='Tenant Info'!A11 | B11: ='Space mix'!B11 | C11: ='Tenant Info'!H11 | D11: ='Tenant Info'!C11 | E11: ='Tenant Info'!D11
A12: ='Tenant Info'!A12 | B12: ='Space mix'!B12 | C12: ='Tenant Info'!H12 | D12: ='Tenant Info'!C12 | E12: ='Tenant Info'!D12
A13: ='Tenant Info'!A13 | B13: ='Space mix'!B13 | C13: ='Tenant Info'!H13 | D13: ='Tenant Info'!C13 | E13: ='Tenant Info'!D13
A14: ='Tenant Info'!A14 | B14: ='Space mix'!B14 | C14: ='Tenant Info'!H14 | D14: ='Tenant Info'!C14 | E14: ='Tenant Info'!D14
... A1999: ='Tenant Info'!A1999 | B1999: ='Space mix'!B1999 | C1999: ='Tenant Info'!H1999 | D1999: ='Tenant Info'!C1999 | E1999: ='Tenant Info'!D1999

Sheet PromotionsDiscounts
A1: ='Space mix'!A1 -> Space | B1: ='Tenant Info'!C1 -> First Name | C1: ='Tenant Info'!D1 -> Last Name | D1: Promotion | E1: Promotion Type | F1: Promotion Value | G1: Promotion Start | H1: Promotion Length | I1: Discount | J1: Discount Type | K1: Discount Value
A2: ='Space mix'!A2 -> 101 or A-101 | B2: ='Tenant Info'!C2 -> Joe | C2: ='Tenant Info'!D2 -> Doe | D2: [Promotion Name] | E2: [Promotion Fixed/Percentage/Dollar] | F2: 10 or 10.05 | G2: DD/MM/YYYY | H2: [Promotion Length Months] | I2: [Discount Name] | J2: [Discount Fixed/Percentage/Dollar] | K2: [Amount]
A3: ='Tenant Info'!A3 | B3: ='Tenant Info'!C3 | C3: ='Tenant Info'!D3
A4: ='Tenant Info'!A4 | B4: ='Tenant Info'!C4 | C4: ='Tenant Info'!D4
A5: ='Tenant Info'!A5 | B5: ='Tenant Info'!C5 | C5: ='Tenant Info'!D5
A6: ='Tenant Info'!A6 | B6: ='Tenant Info'!C6 | C6: ='Tenant Info'!D6
A7: ='Tenant Info'!A7 | B7: ='Tenant Info'!C7 | C7: ='Tenant Info'!D7
A8: ='Tenant Info'!A8 | B8: ='Tenant Info'!C8 | C8: ='Tenant Info'!D8
A9: ='Tenant Info'!A9 | B9: ='Tenant Info'!C9 | C9: ='Tenant Info'!D9
A10: ='Tenant Info'!A10 | B10: ='Tenant Info'!C10 | C10: ='Tenant Info'!D10
A11: ='Tenant Info'!A11 | B11: ='Tenant Info'!C11 | C11: ='Tenant Info'!D11
A12: ='Tenant Info'!A12 | B12: ='Tenant Info'!C12 | C12: ='Tenant Info'!D12
A13: ='Tenant Info'!A13 | B13: ='Tenant Info'!C13 | C13: ='Tenant Info'!D13
A14: ='Tenant Info'!A14 | B14: ='Tenant Info'!C14 | C14: ='Tenant Info'!D14
... A999: ='Tenant Info'!A999 | B999: ='Tenant Info'!C999 | C999: ='Tenant Info'!D999

Sheet Tenant Payment info
A1: ='Space mix'!A1 -> Space | B1: ='Space mix'!B1 | C1: ='Tenant Info'!C1 -> First Name | D1: ='Tenant Info'!D1 -> Last Name | E1: ='Tenant Info'!F1 -> Rent | F1: Last Rent Change Date | G1: ='Tenant Info'!G1 -> Move In Date | H1: Paid Date | I1: Bill Day | J1: Paid Through Date | K1: Validation FOM Only (Please see comment for instructions) | M1: Rent Balance | N1: Late Fees Balance | O1: Lien Fees Balance | P1: Fees Balance | Q1: Prepaid Rent | R1: Prepaid Additional Rent/Premium | S1: Tax Balance | T1: Prepaid Tax | U1: Security Deposit | V1: Security Deposit Balance | W1: Protection/Insurance Balance | X1: Protection/Insurance Provider | Y1: Protection/Insurance Coverage | Z1: Additional Rent/Premium | AA1: Merchandise Balance
A2: ='Space mix'!A2 -> 101 or A-101 | B2: ='Space mix'!B2 -> Occupied or Vacant | C2: ='Tenant Info'!C2 -> Joe | D2: ='Tenant Info'!D2 -> Doe | E2: ='Tenant Info'!F2 -> 100 or 100.05 | F2: MM/DD/YYYY | G2: ='Tenant Info'!G2 -> MM/DD/YYYY | H2: MM/DD/YYYY | I2: 1 | J2: MM/DD/YYYY | N2: 10 or 10.05 | O2: 10 or 10.06 | P2: 100 or 100.05 | Q2: 100 or 100.05 | R2: 9 or 9.05 | S2: 100 or 100.05 | T2: 100 or 100.05 | U2: 100 or 100.05 | V2: 100 or 100.05 | W2: 2 or 2.05 | X2: Storelocal Protection | Y2: 2500 | Z2: 9 or 9.05 | AA2: 9 or 9.05
A3: ='Tenant Info'!A3 | B3: ='Space mix'!B3 | C3: ='Tenant Info'!C3 | D3: ='Tenant Info'!D3 | E3: ='Tenant Info'!F3 | K3: =datedif(J3,$K$2,"m") | L3: =K3*E3
A4: ='Tenant Info'!A4 | B4: ='Space mix'!B4 | C4: ='Tenant Info'!C4 | D4: ='Tenant Info'!D4 | E4: ='Tenant Info'!F4
A5: ='Tenant Info'!A5 | B5: ='Space mix'!B5 | C5: ='Tenant Info'!C5 | D5: ='Tenant Info'!D5 | E5: ='Tenant Info'!F5
A6: ='Tenant Info'!A6 | B6: ='Space mix'!B6 | C6: ='Tenant Info'!C6 | D6: ='Tenant Info'!D6 | E6: ='Tenant Info'!F6
A7: ='Tenant Info'!A7 | B7: ='Space mix'!B7 | C7: ='Tenant Info'!C7 | D7: ='Tenant Info'!D7 | E7: ='Tenant Info'!F7
A8: ='Tenant Info'!A8 | B8: ='Space mix'!B8 | C8: ='Tenant Info'!C8 | D8: ='Tenant Info'!D8 | E8: ='Tenant Info'!F8
A9: ='Tenant Info'!A9 | B9: ='Space mix'!B9 | C9: ='Tenant Info'!C9 | D9: ='Tenant Info'!D9 | E9: ='Tenant Info'!F9
A10: ='Tenant Info'!A10 | B10: ='Space mix'!B10 | C10: ='Tenant Info'!C10 | D10: ='Tenant Info'!D10 | E10: ='Tenant Info'!F10
A11: ='Tenant Info'!A11 | B11: ='Space mix'!B11 | C11: ='Tenant Info'!C11 | D11: ='Tenant Info'!D11 | E11: ='Tenant Info'!F11
A12: ='Tenant Info'!A12 | B12: ='Space mix'!B12 | C12: ='Tenant Info'!C12 | D12: ='Tenant Info'!D12 | E12: ='Tenant Info'!F12
A13: ='Tenant Info'!A13 | B13: ='Space mix'!B13 | C13: ='Tenant Info'!C13 | D13: ='Tenant Info'!D13 | E13: ='Tenant Info'!F13
A14: ='Tenant Info'!A14 | B14: ='Space mix'!B14 | C14: ='Tenant Info'!C14 | D14: ='Tenant Info'!D14 | E14: ='Tenant Info'!F14
A15: ='Tenant Info'!A15 | B15: ='Space mix'!B15 | C15: ='Tenant Info'!C15 | D15: ='Tenant Info'!D15 | E15: ='Tenant Info'!F15
... A79: ='Tenant Info'!A79 | B79: ='Space mix'!B79 | C79: ='Tenant Info'!C79 | D79: ='Tenant Info'!D79 | E79: ='Tenant Info'!F79
A80: ='Tenant Info'!A80 | B80: ='Space mix'!B80 | C80: ='Tenant Info'!C80 | D80: ='Tenant Info'!D80 | E80: ='Tenant Info'!F80 | K80: =datedif(J80,$K$2,"m")
A81: ='Tenant Info'!A81 | B81: ='Space mix'!B81 | C81: ='Tenant Info'!C81 | D81: ='Tenant Info'!D81 | E81: ='Tenant Info'!F81
A82: ='Tenant Info'!A82 | B82: ='Space mix'!B82 | C82: ='Tenant Info'!C82 | D82: ='Tenant Info'!D82 | E82: ='Tenant Info'!F82
A83: ='Tenant Info'!A83 | B83: ='Space mix'!B83 | C83: ='Tenant Info'!C83 | D83: ='Tenant Info'!D83 | E83: ='Tenant Info'!F83
A84: ='Tenant Info'!A84 | B84: ='Space mix'!B84 | C84: ='Tenant Info'!C84 | D84: ='Tenant Info'!D84 | E84: ='Tenant Info'!F84
A85: ='Tenant Info'!A85 | B85: ='Space mix'!B85 | C85: ='Tenant Info'!C85 | D85: ='Tenant Info'!D85 | E85: ='Tenant Info'!F85
A86: ='Tenant Info'!A86 | B86: ='Space mix'!B86 | C86: ='Tenant Info'!C86 | D86: ='Tenant Info'!D86 | E86: ='Tenant Info'!F86
A87: ='Tenant Info'!A87 | B87: ='Space mix'!B87 | C87: ='Tenant Info'!C87 | D87: ='Tenant Info'!D87 | E87: ='Tenant Info'!F87
A88: ='Tenant Info'!A88 | B88: ='Space mix'!B88 | C88: ='Tenant Info'!C88 | D88: ='Tenant Info'!D88 | E88: ='Tenant Info'!F88
A89: ='Tenant Info'!A89 | B89: ='Space mix'!B89 | C89: ='Tenant Info'!C89 | D89: ='Tenant Info'!D89 | E89: ='Tenant Info'!F89
A90: ='Tenant Info'!A90 | B90: ='Space mix'!B90 | C90: ='Tenant Info'!C90 | D90: ='Tenant Info'!D90 | E90: ='Tenant Info'!F90
A91: ='Tenant Info'!A91 | B91: ='Space mix'!B91 | C91: ='Tenant Info'!C91 | D91: ='Tenant Info'!D91 | E91: ='Tenant Info'!F91
A92: ='Tenant Info'!A92 | B92: ='Space mix'!B92 | C92: ='Tenant Info'!C92 | D92: ='Tenant Info'!D92 | E92: ='Tenant Info'!F92
... A149: ='Tenant Info'!A149 | B149: ='Space mix'!B149 | C149: ='Tenant Info'!C149 | D149: ='Tenant Info'!D149 | E149: ='Tenant Info'!F149
A150: ='Tenant Info'!A150 | B150: ='Space mix'!B150 | C150: ='Tenant Info'!C150 | D150: ='Tenant Info'!D150 | E150: ='Tenant Info'!F150 | K150: =datedif(J150,$K$2,"m")
A151: ='Tenant Info'!A151 | B151: ='Space mix'!B151 | C151: ='Tenant Info'!C151 | D151: ='Tenant Info'!D151 | E151: ='Tenant Info'!F151
A152: ='Tenant Info'!A152 | B152: ='Space mix'!B152 | C152: ='Tenant Info'!C152 | D152: ='Tenant Info'!D152 | E152: ='Tenant Info'!F152
A153: ='Tenant Info'!A153 | B153: ='Space mix'!B153 | C153: ='Tenant Info'!C153 | D153: ='Tenant Info'!D153 | E153: ='Tenant Info'!F153
A154: ='Tenant Info'!A154 | B154: ='Space mix'!B154 | C154: ='Tenant Info'!C154 | D154: ='Tenant Info'!D154 | E154: ='Tenant Info'!F154
A155: ='Tenant Info'!A155 | B155: ='Space mix'!B155 | C155: ='Tenant Info'!C155 | D155: ='Tenant Info'!D155 | E155: ='Tenant Info'!F155
A156: ='Tenant Info'!A156 | B156: ='Space mix'!B156 | C156: ='Tenant Info'!C156 | D156: ='Tenant Info'!D156 | E156: ='Tenant Info'!F156
A157: ='Tenant Info'!A157 | B157: ='Space mix'!B157 | C157: ='Tenant Info'!C157 | D157: ='Tenant Info'!D157 | E157: ='Tenant Info'!F157
A158: ='Tenant Info'!A158 | B158: ='Space mix'!B158 | C158: ='Tenant Info'!C158 | D158: ='Tenant Info'!D158 | E158: ='Tenant Info'!F158
A159: ='Tenant Info'!A159 | B159: ='Space mix'!B159 | C159: ='Tenant Info'!C159 | D159: ='Tenant Info'!D159 | E159: ='Tenant Info'!F159
A160: ='Tenant Info'!A160 | B160: ='Space mix'!B160 | C160: ='Tenant Info'!C160 | D160: ='Tenant Info'!D160 | E160: ='Tenant Info'!F160
A161: ='Tenant Info'!A161 | B161: ='Space mix'!B161 | C161: ='Tenant Info'!C161 | D161: ='Tenant Info'!D161 | E161: ='Tenant Info'!F161
A162: ='Tenant Info'!A162 | B162: ='Space mix'!B162 | C162: ='Tenant Info'!C162 | D162: ='Tenant Info'!D162 | E162: ='Tenant Info'!F162
... A176: ='Tenant Info'!A176 | B176: ='Space mix'!B176 | C176: ='Tenant Info'!C176 | D176: ='Tenant Info'!D176 | E176: ='Tenant Info'!F176
A177: ='Tenant Info'!A177 | B177: ='Space mix'!B177 | C177: ='Tenant Info'!C177 | D177: ='Tenant Info'!D177 | E177: ='Tenant Info'!F177 | K177: =datedif(J177,$K$2,"m")
A178: ='Tenant Info'!A178 | B178: ='Space mix'!B178 | C178: ='Tenant Info'!C178 | D178: ='Tenant Info'!D178 | E178: ='Tenant Info'!F178
A179: ='Tenant Info'!A179 | B179: ='Space mix'!B179 | C179: ='Tenant Info'!C179 | D179: ='Tenant Info'!D179 | E179: ='Tenant Info'!F179
A180: ='Tenant Info'!A180 | B180: ='Space mix'!B180 | C180: ='Tenant Info'!C180 | D180: ='Tenant Info'!D180 | E180: ='Tenant Info'!F180
A181: ='Tenant Info'!A181 | B181: ='Space mix'!B181 | C181: ='Tenant Info'!C181 | D181: ='Tenant Info'!D181 | E181: ='Tenant Info'!F181
A182: ='Tenant Info'!A182 | B182: ='Space mix'!B182 | C182: ='Tenant Info'!C182 | D182: ='Tenant Info'!D182 | E182: ='Tenant Info'!F182
A183: ='Tenant Info'!A183 | B183: ='Space mix'!B183 | C183: ='Tenant Info'!C183 | D183: ='Tenant Info'!D183 | E183: ='Tenant Info'!F183
A184: ='Tenant Info'!A184 | B184: ='Space mix'!B184 | C184: ='Tenant Info'!C184 | D184: ='Tenant Info'!D184 | E184: ='Tenant Info'!F184
A185: ='Tenant Info'!A185 | B185: ='Space mix'!B185 | C185: ='Tenant Info'!C185 | D185: ='Tenant Info'!D185 | E185: ='Tenant Info'!F185
A186: ='Tenant Info'!A186 | B186: ='Space mix'!B186 | C186: ='Tenant Info'!C186 | D186: ='Tenant Info'!D186 | E186: ='Tenant Info'!F186
A187: ='Tenant Info'!A187 | B187: ='Space mix'!B187 | C187: ='Tenant Info'!C187 | D187: ='Tenant Info'!D187 | E187: ='Tenant Info'!F187
A188: ='Tenant Info'!A188 | B188: ='Space mix'!B188 | C188: ='Tenant Info'!C188 | D188: ='Tenant Info'!D188 | E188: ='Tenant Info'!F188
A189: ='Tenant Info'!A189 | B189: ='Space mix'!B189 | C189: ='Tenant Info'!C189 | D189: ='Tenant Info'!D189 | E189: ='Tenant Info'!F189 | K189: =datedif(J189,$K$2,"m")
A190: ='Tenant Info'!A190 | B190: ='Space mix'!B190 | C190: ='Tenant Info'!C190 | D190: ='Tenant Info'!D190 | E190: ='Tenant Info'!F190
A191: ='Tenant Info'!A191 | B191: ='Space mix'!B191 | C191: ='Tenant Info'!C191 | D191: ='Tenant Info'!D191 | E191: ='Tenant Info'!F191
A192: ='Tenant Info'!A192 | B192: ='Space mix'!B192 | C192: ='Tenant Info'!C192 | D192: ='Tenant Info'!D192 | E192: ='Tenant Info'!F192
A193: ='Tenant Info'!A193 | B193: ='Space mix'!B193 | C193: ='Tenant Info'!C193 | D193: ='Tenant Info'!D193 | E193: ='Tenant Info'!F193
A194: ='Tenant Info'!A194 | B194: ='Space mix'!B194 | C194: ='Tenant Info'!C194 | D194: ='Tenant Info'!D194 | E194: ='Tenant Info'!F194
A195: ='Tenant Info'!A195 | B195: ='Space mix'!B195 | C195: ='Tenant Info'!C195 | D195: ='Tenant Info'!D195 | E195: ='Tenant Info'!F195
A196: ='Tenant Info'!A196 | B196: ='Space mix'!B196 | C196: ='Tenant Info'!C196 | D196: ='Tenant Info'!D196 | E196: ='Tenant Info'!F196
A197: ='Tenant Info'!A197 | B197: ='Space mix'!B197 | C197: ='Tenant Info'!C197 | D197: ='Tenant Info'!D197 | E197: ='Tenant Info'!F197
A198: ='Tenant Info'!A198 | B198: ='Space mix'!B198 | C198: ='Tenant Info'!C198 | D198: ='Tenant Info'!D198 | E198: ='Tenant Info'!F198
A199: ='Tenant Info'!A199 | B199: ='Space mix'!B199 | C199: ='Tenant Info'!C199 | D199: ='Tenant Info'!D199 | E199: ='Tenant Info'!F199
A200: ='Tenant Info'!A200 | B200: ='Space mix'!B200 | C200: ='Tenant Info'!C200 | D200: ='Tenant Info'!D200 | E200: ='Tenant Info'!F200
A201: ='Tenant Info'!A201 | B201: ='Space mix'!B201 | C201: ='Tenant Info'!C201 | D201: ='Tenant Info'!D201 | E201: ='Tenant Info'!F201
... A228: ='Tenant Info'!A228 | B228: ='Space mix'!B228 | C228: ='Tenant Info'!C228 | D228: ='Tenant Info'!D228 | E228: ='Tenant Info'!F228
A229: ='Tenant Info'!A229 | B229: ='Space mix'!B229 | C229: ='Tenant Info'!C229 | D229: ='Tenant Info'!D229 | E229: ='Tenant Info'!F229 | K229: =datedif(J229,$K$2,"m")
A230: ='Tenant Info'!A230 | B230: ='Space mix'!B230 | C230: ='Tenant Info'!C230 | D230: ='Tenant Info'!D230 | E230: ='Tenant Info'!F230
A231: ='Tenant Info'!A231 | B231: ='Space mix'!B231 | C231: ='Tenant Info'!C231 | D231: ='Tenant Info'!D231 | E231: ='Tenant Info'!F231
A232: ='Tenant Info'!A232 | B232: ='Space mix'!B232 | C232: ='Tenant Info'!C232 | D232: ='Tenant Info'!D232 | E232: ='Tenant Info'!F232
A233: ='Tenant Info'!A233 | B233: ='Space mix'!B233 | C233: ='Tenant Info'!C233 | D233: ='Tenant Info'!D233 | E233: ='Tenant Info'!F233
A234: ='Tenant Info'!A234 | B234: ='Space mix'!B234 | C234: ='Tenant Info'!C234 | D234: ='Tenant Info'!D234 | E234: ='Tenant Info'!F234
A235: ='Tenant Info'!A235 | B235: ='Space mix'!B235 | C235: ='Tenant Info'!C235 | D235: ='Tenant Info'!D235 | E235: ='Tenant Info'!F235
A236: ='Tenant Info'!A236 | B236: ='Space mix'!B236 | C236: ='Tenant Info'!C236 | D236: ='Tenant Info'!D236 | E236: ='Tenant Info'!F236
A237: ='Tenant Info'!A237 | B237: ='Space mix'!B237 | C237: ='Tenant Info'!C237 | D237: ='Tenant Info'!D237 | E237: ='Tenant Info'!F237
A238: ='Tenant Info'!A238 | B238: ='Space mix'!B238 | C238: ='Tenant Info'!C238 | D238: ='Tenant Info'!D238 | E238: ='Tenant Info'!F238
A239: ='Tenant Info'!A239 | B239: ='Space mix'!B239 | C239: ='Tenant Info'!C239 | D239: ='Tenant Info'!D239 | E239: ='Tenant Info'!F239
A240: ='Tenant Info'!A240 | B240: ='Space mix'!B240 | C240: ='Tenant Info'!C240 | D240: ='Tenant Info'!D240 | E240: ='Tenant Info'!F240
A241: ='Tenant Info'!A241 | B241: ='Space mix'!B241 | C241: ='Tenant Info'!C241 | D241: ='Tenant Info'!D241 | E241: ='Tenant Info'!F241
... A249: ='Tenant Info'!A249 | B249: ='Space mix'!B249 | C249: ='Tenant Info'!C249 | D249: ='Tenant Info'!D249 | E249: ='Tenant Info'!F249
A250: ='Tenant Info'!A250 | B250: ='Space mix'!B250 | C250: ='Tenant Info'!C250 | D250: ='Tenant Info'!D250 | E250: ='Tenant Info'!F250 | K250: =datedif(J250,$K$2,"m")
A251: ='Tenant Info'!A251 | B251: ='Space mix'!B251 | C251: ='Tenant Info'!C251 | D251: ='Tenant Info'!D251 | E251: ='Tenant Info'!F251
A252: ='Tenant Info'!A252 | B252: ='Space mix'!B252 | C252: ='Tenant Info'!C252 | D252: ='Tenant Info'!D252 | E252: ='Tenant Info'!F252
A253: ='Tenant Info'!A253 | B253: ='Space mix'!B253 | C253: ='Tenant Info'!C253 | D253: ='Tenant Info'!D253 | E253: ='Tenant Info'!F253
A254: ='Tenant Info'!A254 | B254: ='Space mix'!B254 | C254: ='Tenant Info'!C254 | D254: ='Tenant Info'!D254 | E254: ='Tenant Info'!F254
A255: ='Tenant Info'!A255 | B255: ='Space mix'!B255 | C255: ='Tenant Info'!C255 | D255: ='Tenant Info'!D255 | E255: ='Tenant Info'!F255
A256: ='Tenant Info'!A256 | B256: ='Space mix'!B256 | C256: ='Tenant Info'!C256 | D256: ='Tenant Info'!D256 | E256: ='Tenant Info'!F256
A257: ='Tenant Info'!A257 | B257: ='Space mix'!B257 | C257: ='Tenant Info'!C257 | D257: ='Tenant Info'!D257 | E257: ='Tenant Info'!F257
A258: ='Tenant Info'!A258 | B258: ='Space mix'!B258 | C258: ='Tenant Info'!C258 | D258: ='Tenant Info'!D258 | E258: ='Tenant Info'!F258
A259: ='Tenant Info'!A259 | B259: ='Space mix'!B259 | C259: ='Tenant Info'!C259 | D259: ='Tenant Info'!D259 | E259: ='Tenant Info'!F259
A260: ='Tenant Info'!A260 | B260: ='Space mix'!B260 | C260: ='Tenant Info'!C260 | D260: ='Tenant Info'!D260 | E260: ='Tenant Info'!F260
A261: ='Tenant Info'!A261 | B261: ='Space mix'!B261 | C261: ='Tenant Info'!C261 | D261: ='Tenant Info'!D261 | E261: ='Tenant Info'!F261
A262: ='Tenant Info'!A262 | B262: ='Space mix'!B262 | C262: ='Tenant Info'!C262 | D262: ='Tenant Info'!D262 | E262: ='Tenant Info'!F262
... A316: ='Tenant Info'!A316 | B316: ='Space mix'!B316 | C316: ='Tenant Info'!C316 | D316: ='Tenant Info'!D316 | E316: ='Tenant Info'!F316
A317: ='Tenant Info'!A317 | B317: ='Space mix'!B317 | C317: ='Tenant Info'!C317 | D317: ='Tenant Info'!D317 | E317: ='Tenant Info'!F317 | K317: =datedif(J317,$K$2,"m")
A318: ='Tenant Info'!A318 | B318: ='Space mix'!B318 | C318: ='Tenant Info'!C318 | D318: ='Tenant Info'!D318 | E318: ='Tenant Info'!F318
...

Sheet Final Sheet (View Only)
A1: Owner | B1: Name | C1: Building | D1: Occupied or Vacant | E1: ='Space mix'!A1 -> Space | F1: ='Space mix'!D1 -> Width | G1: ='Space mix'!E1 -> Length | H1: ='Space mix'!F1 -> Height | I1: ='Space mix'!G1 -> Rate | J1: Web Rate (not there on app right now) | K1: ='Space mix'!L1 -> Space Size | L1: ='Space mix'!H1 -> Space Category | M1: ='Space mix'!C1 -> Space Type | N1: ='Space mix'!J1 -> Door Width | O1: ='Space mix'!K1 -> Door Height | P1: Amenities | Q1: ='Space mix'!M1 -> Sq. Ft. | R1: ='Space mix'!I1 -> Floor | S1: ='Tenant Info'!C1 -> First Name | T1: ='Tenant Info'!D1 -> Last Name | U1: ='Tenant Info'!E1 -> Middle Name | V1: ='Tenant Info'!I1 -> Account Code | W1: ='Tenant Info'!J1 -> Address | X1: ='Tenant Info'!K1 -> City | Y1: ='Tenant Info'!L1 -> State | Z1: ='Tenant Info'!M1 -> ZIP | AA1: ='Tenant Info'!N1 -> Country | AB1: ='Tenant Info'!O1 -> Email | AC1: ='Tenant Info'!P1 -> Cell Phone | ... AF1: ='Tenant Info'!S1 -> Access Code | AG1: DOB | AH1: Gender | AI1: ='Tenant Info'!H1 -> Active Military | AJ1: ='Tenant Info'!T1 -> DL Id | AK1: ='Tenant Info'!U1 -> DL State | AL1: ='Tenant Info'!V1 -> DL City | AM1: ='Tenant Info'!W1 -> DL Exp Date | AN1: ='Tenant Info'!F1 -> Rent | AO1: ='Tenant Payment info'!F1 -> Last Rent Change Date | AP1: ='Tenant Info'!G1 -> Move In Date | AQ1: Move Out Date | AR1: ='Tenant Payment info'!H1 -> Paid Date | AS1: ='Tenant Payment info'!I1 -> Bill Day | AT1: ='Tenant Payment info'!J1 -> Paid Through Date | AU1: ='Tenant Info'!X1 -> Alt First Name | AV1: ='Tenant Info'!Y1 -> Alt Last Name | AW1: ='Tenant Info'!Z1 -> Alt Middle Name | AX1: ='Tenant Info'!AA1 -> Alt Address | AY1: ='Tenant Info'!AB1 -> Alt City | AZ1: ='Tenant Info'!AC1 -> Alt State | BA1: ='Tenant Info'!AD1 -> Alt ZIP | BB1: ='Tenant Info'!AE1 -> Alt Email | ... BE1: ='Tenant Info'!AH1 -> Alt Cell Phone | BF1: ='Tenant Payment info'!U1 -> Security Deposit | BG1: ='Tenant Payment info'!V1 -> Security Deposit Balance | BH1: ='Tenant Payment info'!M1 -> Rent Balance | BI1: ='Tenant Payment info'!P1 -> Fees Balance | BJ1: ='Tenant Payment info'!W1 -> Protection/Insurance Balance | BK1: ='Tenant Payment info'!AA1 -> Merchandise Balance | BL1: ='Tenant Payment info'!N1 -> Late Fees Balance | BM1: ='Tenant Payment info'!O1 -> Lien Fees Balance | BN1: ='Tenant Payment info'!S1 -> Tax Balance | BO1: ='Tenant Payment info'!Q1 -> Prepaid Rent | BP1: ='Tenant Payment info'!R1 -> Prepaid Additional Rent/Premium | BQ1: ='Tenant Payment info'!T1 -> Prepaid Tax | BR1: ='Tenant Payment info'!X1 -> Protection/Insurance Provider | BS1: ='Tenant Payment info'!Y1 -> Protection/Insurance Coverage | BT1: ='Tenant Payment info'!Z1 -> Additional Rent/Premium | BU1: Delinquency Status | BV1: Lien Status | BW1: Lien Posted Date | BX1: =PromotionsDiscounts!D1 -> Promotion | BY1: =PromotionsDiscounts!E1 -> Promotion Type | BZ1: =PromotionsDiscounts!F1 -> Promotion Value | CA1: =PromotionsDiscounts!G1 -> Promotion Start | CB1: =PromotionsDiscounts!H1 -> Promotion Length | CC1: =PromotionsDiscounts!I1 -> Discount | CD1: =PromotionsDiscounts!J1 -> Discount Type | CE1: =PromotionsDiscounts!K1 -> Discount Value | CF1: ='Tenants Military Information'!F1 -> Commanding Officer First Name | CG1: ='Tenants Military Information'!G1 -> Commanding Officer Last Name | CH1: ='Tenants Military Information'!H1 -> Commanding Officer Phone | CI1: ='Tenants Military Information'!I1 -> Commanding Officer Email | CJ1: ='Tenants Military Information'!J1 -> Rank | CK1: ='Tenants Military Information'!K1 -> Military Serial Number | CL1: ='Tenants Military Information'!L1 -> Military Email | CM1: ='Tenants Military Information'!M1 -> Service Member DOB | ... CV1: ='Tenants Military Information'!V1 -> Military Unit Zipcode | CW1: ='Tenants Lien Holder Information'!E1 -> Lien Holder First Name | CX1: ='Tenants Lien Holder Information'!F1 -> Lien Holder Last Name | CY1: ='Tenants Lien Holder Information'!G1 -> Lien Holder Email | CZ1: ='Tenants Lien Holder Information'!H1 -> Lien Holder Phone | DA1: ='Tenants Lien Holder Information'!I1 -> Lien Holder Address 1 | DB1: ='Tenants Lien Holder Information'!J1 -> Lien Holder Address 2 | DC1: ='Tenants Lien Holder Information'!K1 -> Lien Holder City | DD1: ='Tenants Lien Holder Information'!L1 -> Lien Holder State | DE1: ='Tenants Lien Holder Information'!M1 -> Lien Holder Zipcode
D2: ='Space mix'!B2 | E2: ='Space mix'!A2 | F2: ='Space mix'!D2 | G2: ='Space mix'!E2 | H2: ='Space mix'!F2 | I2: ='Space mix'!G2 | K2: ='Space mix'!L2 | L2: ='Space mix'!H2 | M2: ='Space mix'!C2 | N2: ='Space mix'!J2 | O2: ='Space mix'!K2 | Q2: ='Space mix'!M2 | R2: ='Space mix'!I2 | S2: ='Tenant Info'!C2 | T2: ='Tenant Info'!D2 | U2: ='Tenant Info'!E2 | V2: ='Tenant Info'!I2 | W2: ='Tenant Info'!J2 | X2: ='Tenant Info'!K2 | Y2: ='Tenant Info'!L2 | Z2: ='Tenant Info'!M2 | AA2: ='Tenant Info'!N2 | AB2: ='Tenant Info'!O2 | AC2: ='Tenant Info'!P2 | ... AF2: ='Tenant Info'!S2 | AI2: ='Tenant Info'!H2 | AJ2: ='Tenant Info'!T2 | AK2: ='Tenant Info'!U2 | AL2: ='Tenant Info'!V2 | AM2: ='Tenant Info'!W2 | AN2: ='Tenant Info'!F2 | AO2: ='Tenant Payment info'!F2 | AP2: ='Tenant Info'!G2 | AR2: ='Tenant Payment info'!H2 | AS2: ='Tenant Payment info'!I2 | AT2: ='Tenant Payment info'!J2 | AU2: ='Tenant Info'!X2 | AV2: ='Tenant Info'!Y2 | AW2: ='Tenant Info'!Z2 | AX2: ='Tenant Info'!AA2 | AY2: ='Tenant Info'!AB2 | AZ2: ='Tenant Info'!AC2 | BA2: ='Tenant Info'!AD2 | BB2: ='Tenant Info'!AE2 | ... BE2: ='Tenant Info'!AH2 | BF2: ='Tenant Payment info'!U2 | BG2: ='Tenant Payment info'!V2 | BH2: ='Tenant Payment info'!M2 | BI2: ='Tenant Payment info'!P2 | BJ2: ='Tenant Payment info'!W2 | BK2: ='Tenant Payment info'!AA2 | BL2: ='Tenant Payment info'!N2 | BM2: ='Tenant Payment info'!O2 | BN2: ='Tenant Payment info'!S2 | BO2: ='Tenant Payment info'!Q2 | BP2: ='Tenant Payment info'!R2 | BQ2: ='Tenant Payment info'!T2 | BR2: ='Tenant Payment info'!X2 | BS2: ='Tenant Payment info'!Y2 | BT2: ='Tenant Payment info'!Z2 | BX2: =PromotionsDiscounts!D2 | BY2: =PromotionsDiscounts!E2 | BZ2: =PromotionsDiscounts!F2 | CA2: =PromotionsDiscounts!G2 | CB2: =PromotionsDiscounts!H2 | CC2: =PromotionsDiscounts!I2 | CD2: =PromotionsDiscounts!J2 | CE2: =PromotionsDiscounts!K2 | CF2: ='Tenants Military Information'!F2 | CG2: ='Tenants Military Information'!G2 | CH2: ='Tenants Military Information'!H2 | CI2: ='Tenants Military Information'!I2 | CJ2: ='Tenants Military Information'!J2 | CK2: ='Tenants Military Information'!K2 | CL2: ='Tenants Military Information'!L2 | CM2: ='Tenants Military Information'!M2 | ... CV2: ='Tenants Military Information'!V2 | CW2: ='Tenants Lien Holder Information'!E2 | CX2: ='Tenants Lien Holder Information'!F2 | CY2: ='Tenants Lien Holder Information'!G2 | CZ2: ='Tenants Lien Holder Information'!H2 | DA2: ='Tenants Lien Holder Information'!I2 | DB2: ='Tenants Lien Holder Information'!J2 | DC2: ='Tenants Lien Holder Information'!K2 | DD2: ='Tenants Lien Holder Information'!L2 | DE2: ='Tenants Lien Holder Information'!M2
D3: ='Space mix'!B3 | E3: ='Space mix'!A3 | F3: ='Space mix'!D3 | G3: ='Space mix'!E3 | H3: ='Space mix'!F3 | I3: ='Space mix'!G3 | J3: =I3 | K3: ='Space mix'!L3 | L3: ='Space mix'!H3 | M3: ='Space mix'!C3 | N3: ='Space mix'!J3 | O3: ='Space mix'!K3 | Q3: ='Space mix'!M3 | R3: ='Space mix'!I3 | S3: ='Tenant Info'!C3 | T3: ='Tenant Info'!D3 | U3: ='Tenant Info'!E3 | V3: ='Tenant Info'!I3 | W3: ='Tenant Info'!J3 | X3: ='Tenant Info'!K3 | Y3: ='Tenant Info'!L3 | Z3: ='Tenant Info'!M3 | AA3: ='Tenant Info'!N3 | AB3: ='Tenant Info'!O3 | AC3: ='Tenant Info'!P3 | ... AF3: ='Tenant Info'!S3 | AI3: ='Tenant Info'!H3 | AJ3: ='Tenant Info'!T3 | AK3: ='Tenant Info'!U3 | AL3: ='Tenant Info'!V3 | AM3: ='Tenant Info'!W3 | AN3: ='Tenant Info'!F3 | AP3: ='Tenant Info'!G3 | AR3: ='Tenant Payment info'!H3 | AS3: ='Tenant Payment info'!I3 | AT3: ='Tenant Payment info'!J3 | AU3: ='Tenant Info'!X3 | AV3: ='Tenant Info'!Y3 | AW3: ='Tenant Info'!Z3 | AX3: ='Tenant Info'!AA3 | AY3: ='Tenant Info'!AB3 | AZ3: ='Tenant Info'!AC3 | BA3: ='Tenant Info'!AD3 | BB3: ='Tenant Info'!AE3 | ... BE3: ='Tenant Info'!AH3 | BF3: ='Tenant Payment info'!U3 | BG3: ='Tenant Payment info'!V3 | BH3: ='Tenant Payment info'!M3 | BI3: ='Tenant Payment info'!P3 | BJ3: ='Tenant Payment info'!W3 | BK3: ='Tenant Payment info'!AA3 | BL3: ='Tenant Payment info'!N3 | BM3: ='Tenant Payment info'!O3 | BN3: ='Tenant Payment info'!S3 | BO3: ='Tenant Payment info'!Q3 | BP3: ='Tenant Payment info'!R3 | BQ3: ='Tenant Payment info'!T3 | BR3: ='Tenant Payment info'!X3 | BS3: ='Tenant Payment info'!Y3 | BT3: ='Tenant Payment info'!Z3 | BX3: =PromotionsDiscounts!D3 | BY3: =PromotionsDiscounts!E3 | BZ3: =PromotionsDiscounts!F3 | CA3: =PromotionsDiscounts!G3 | CB3: =PromotionsDiscounts!H3 | CC3: =PromotionsDiscounts!I3 | CD3: =PromotionsDiscounts!J3 | CE3: =PromotionsDiscounts!K3 | CF3: ='Tenants Military Information'!F3 | CG3: ='Tenants Military Information'!G3 | CH3: ='Tenants Military Information'!H3 | CI3: ='Tenants Military Information'!I3 | CJ3: ='Tenants Military Information'!J3 | CK3: ='Tenants Military Information'!K3 | CL3: ='Tenants Military Information'!L3 | CM3: ='Tenants Military Information'!M3 | ... CV3: ='Tenants Military Information'!V3 | CW3: ='Tenants Lien Holder Information'!E3 | CX3: ='Tenants Lien Holder Information'!F3 | CY3: ='Tenants Lien Holder Information'!G3 | CZ3: ='Tenants Lien Holder Information'!H3 | DA3: ='Tenants Lien Holder Information'!I3 | DB3: ='Tenants Lien Holder Information'!J3 | DC3: ='Tenants Lien Holder Information'!K3 | DD3: ='Tenants Lien Holder Information'!L3 | DE3: ='Tenants Lien Holder Information'!M3
D4: ='Space mix'!B4 | E4: ='Space mix'!A4 | F4: ='Space mix'!D4 | G4: ='Space mix'!E4 | H4: ='Space mix'!F4 | I4: ='Space mix'!G4 | K4: ='Space mix'!L4 | L4: ='Space mix'!H4 | M4: ='Space mix'!C4 | N4: ='Space mix'!J4 | O4: ='Space mix'!K4 | Q4: ='Space mix'!M4 | R4: ='Space mix'!I4 | S4: ='Tenant Info'!C4 | T4: ='Tenant Info'!D4 | U4: ='Tenant Info'!E4 | V4: ='Tenant Info'!I4 | W4: ='Tenant Info'!J4 | X4: ='Tenant Info'!K4 | Y4: ='Tenant Info'!L4 | Z4: ='Tenant Info'!M4 | AA4: ='Tenant Info'!N4 | AB4: ='Tenant Info'!O4 | AC4: ='Tenant Info'!P4 | ... AF4: ='Tenant Info'!S4 | AI4: ='Tenant Info'!H4 | AJ4: ='Tenant Info'!T4 | AK4: ='Tenant Info'!U4 | AL4: ='Tenant Info'!V4 | AM4: ='Tenant Info'!W4 | AN4: ='Tenant Info'!F4 | AP4: ='Tenant Info'!G4 | AR4: ='Tenant Payment info'!H4 | AS4: ='Tenant Payment info'!I4 | AT4: ='Tenant Payment info'!J4 | AU4: ='Tenant Info'!X4 | AV4: ='Tenant Info'!Y4 | AW4: ='Tenant Info'!Z4 | AX4: ='Tenant Info'!AA4 | AY4: ='Tenant Info'!AB4 | AZ4: ='Tenant Info'!AC4 | BA4: ='Tenant Info'!AD4 | BB4: ='Tenant Info'!AE4 | ... BE4: ='Tenant Info'!AH4 | BF4: ='Tenant Payment info'!U4 | BG4: ='Tenant Payment info'!V4 | BH4: ='Tenant Payment info'!M4 | BI4: ='Tenant Payment info'!P4 | BJ4: ='Tenant Payment info'!W4 | BK4: ='Tenant Payment info'!AA4 | BL4: ='Tenant Payment info'!N4 | BM4: ='Tenant Payment info'!O4 | BN4: ='Tenant Payment info'!S4 | BO4: ='Tenant Payment info'!Q4 | BP4: ='Tenant Payment info'!R4 | BQ4: ='Tenant Payment info'!T4 | BR4: ='Tenant Payment info'!X4 | BS4: ='Tenant Payment info'!Y4 | BT4: ='Tenant Payment info'!Z4 | BX4: =PromotionsDiscounts!D4 | BY4: =PromotionsDiscounts!E4 | BZ4: =PromotionsDiscounts!F4 | CA4: =PromotionsDiscounts!G4 | CB4: =PromotionsDiscounts!H4 | CC4: =PromotionsDiscounts!I4 | CD4: =PromotionsDiscounts!J4 | CE4: =PromotionsDiscounts!K4 | CF4: ='Tenants Military Information'!F4 | CG4: ='Tenants Military Information'!G4 | CH4: ='Tenants Military Information'!H4 | CI4: ='Tenants Military Information'!I4 | CJ4: ='Tenants Military Information'!J4 | CK4: ='Tenants Military Information'!K4 | CL4: ='Tenants Military Information'!L4 | CM4: ='Tenants Military Information'!M4 | ... CV4: ='Tenants Military Information'!V4 | CW4: ='Tenants Lien Holder Information'!E4 | CX4: ='Tenants Lien Holder Information'!F4 | CY4: ='Tenants Lien Holder Information'!G4 | CZ4: ='Tenants Lien Holder Information'!H4 | DA4: ='Tenants Lien Holder Information'!I4 | DB4: ='Tenants Lien Holder Information'!J4 | DC4: ='Tenants Lien Holder Information'!K4 | DD4: ='Tenants Lien Holder Information'!L4 | DE4: ='Tenants Lien Holder Information'!M4
D5: ='Space mix'!B5 | E5: ='Space mix'!A5 | F5: ='Space mix'!D5 | G5: ='Space mix'!E5 | H5: ='Space mix'!F5 | I5: ='Space mix'!G5 | K5: ='Space mix'!L5 | L5: ='Space mix'!H5 | M5: ='Space mix'!C5 | N5: ='Space mix'!J5 | O5: ='Space mix'!K5 | Q5: ='Space mix'!M5 | R5: ='Space mix'!I5 | S5: ='Tenant Info'!C5 | T5: ='Tenant Info'!D5 | U5: ='Tenant Info'!E5 | V5: ='Tenant Info'!I5 | W5: ='Tenant Info'!J5 | X5: ='Tenant Info'!K5 | Y5: ='Tenant Info'!L5 | Z5: ='Tenant Info'!M5 | AA5: ='Tenant Info'!N5 | AB5: ='Tenant Info'!O5 | AC5: ='Tenant Info'!P5 | ... AF5: ='Tenant Info'!S5 | AI5: ='Tenant Info'!H5 | AJ5: ='Tenant Info'!T5 | AK5: ='Tenant Info'!U5 | AL5: ='Tenant Info'!V5 | AM5: ='Tenant Info'!W5 | AN5: ='Tenant Info'!F5 | AP5: ='Tenant Info'!G5 | AR5: ='Tenant Payment info'!H5 | AS5: ='Tenant Payment info'!I5 | AT5: ='Tenant Payment info'!J5 | AU5: ='Tenant Info'!X5 | AV5: ='Tenant Info'!Y5 | AW5: ='Tenant Info'!Z5 | AX5: ='Tenant Info'!AA5 | AY5: ='Tenant Info'!AB5 | AZ5: ='Tenant Info'!AC5 | BA5: ='Tenant Info'!AD5 | BB5: ='Tenant Info'!AE5 | ... BE5: ='Tenant Info'!AH5 | BF5: ='Tenant Payment info'!U5 | BG5: ='Tenant Payment info'!V5 | BH5: ='Tenant Payment info'!M5 | BI5: ='Tenant Payment info'!P5 | BJ5: ='Tenant Payment info'!W5 | BK5: ='Tenant Payment info'!AA5 | BL5: ='Tenant Payment info'!N5 | BM5: ='Tenant Payment info'!O5 | BN5: ='Tenant Payment info'!S5 | BO5: ='Tenant Payment info'!Q5 | BP5: ='Tenant Payment info'!R5 | BQ5: ='Tenant Payment info'!T5 | BR5: ='Tenant Payment info'!X5 | BS5: ='Tenant Payment info'!Y5 | BT5: ='Tenant Payment info'!Z5 | BX5: =PromotionsDiscounts!D5 | BY5: =PromotionsDiscounts!E5 | BZ5: =PromotionsDiscounts!F5 | CA5: =PromotionsDiscounts!G5 | CB5: =PromotionsDiscounts!H5 | CC5: =PromotionsDiscounts!I5 | CD5: =PromotionsDiscounts!J5 | CE5: =PromotionsDiscounts!K5 | CF5: ='Tenants Military Information'!F5 | CG5: ='Tenants Military Information'!G5 | CH5: ='Tenants Military Information'!H5 | CI5: ='Tenants Military Information'!I5 | CJ5: ='Tenants Military Information'!J5 | CK5: ='Tenants Military Information'!K5 | CL5: ='Tenants Military Information'!L5 | CM5: ='Tenants Military Information'!M5 | ... CV5: ='Tenants Military Information'!V5 | CW5: ='Tenants Lien Holder Information'!E5 | CX5: ='Tenants Lien Holder Information'!F5 | CY5: ='Tenants Lien Holder Information'!G5 | CZ5: ='Tenants Lien Holder Information'!H5 | DA5: ='Tenants Lien Holder Information'!I5 | DB5: ='Tenants Lien Holder Information'!J5 | DC5: ='Tenants Lien Holder Information'!K5 | DD5: ='Tenants Lien Holder Information'!L5 | DE5: ='Tenants Lien Holder Information'!M5
D6: ='Space mix'!B6 | E6: ='Space mix'!A6 | F6: ='Space mix'!D6 | G6: ='Space mix'!E6 | H6: ='Space mix'!F6 | I6: ='Space mix'!G6 | K6: ='Space mix'!L6 | L6: ='Space mix'!H6 | M6: ='Space mix'!C6 | N6: ='Space mix'!J6 | O6: ='Space mix'!K6 | Q6: ='Space mix'!M6 | R6: ='Space mix'!I6 | S6: ='Tenant Info'!C6 | T6: ='Tenant Info'!D6 | U6: ='Tenant Info'!E6 | V6: ='Tenant Info'!I6 | W6: ='Tenant Info'!J6 | X6: ='Tenant Info'!K6 | Y6: ='Tenant Info'!L6 | Z6: ='Tenant Info'!M6 | AA6: ='Tenant Info'!N6 | AB6: ='Tenant Info'!O6 | AC6: ='Tenant Info'!P6 | ... AF6: ='Tenant Info'!S6 | AI6: ='Tenant Info'!H6 | AJ6: ='Tenant Info'!T6 | AK6: ='Tenant Info'!U6 | AL6: ='Tenant Info'!V6 | AM6: ='Tenant Info'!W6 | AN6: ='Tenant Info'!F6 | AP6: ='Tenant Info'!G6 | AR6: ='Tenant Payment info'!H6 | AS6: ='Tenant Payment info'!I6 | AT6: ='Tenant Payment info'!J6 | AU6: ='Tenant Info'!X6 | AV6: ='Tenant Info'!Y6 | AW6: ='Tenant Info'!Z6 | AX6: ='Tenant Info'!AA6 | AY6: ='Tenant Info'!AB6 | AZ6: ='Tenant Info'!AC6 | BA6: ='Tenant Info'!AD6 | BB6: ='Tenant Info'!AE6 | ... BE6: ='Tenant Info'!AH6 | BF6: ='Tenant Payment info'!U6 | BG6: ='Tenant Payment info'!V6 | BH6: ='Tenant Payment info'!M6 | BI6: ='Tenant Payment info'!P6 | BJ6: ='Tenant Payment info'!W6 | BK6: ='Tenant Payment info'!AA6 | BL6: ='Tenant Payment info'!N6 | BM6: ='Tenant Payment info'!O6 | BN6: ='Tenant Payment info'!S6 | BO6: ='Tenant Payment info'!Q6 | BP6: ='Tenant Payment info'!R6 | BQ6: ='Tenant Payment info'!T6 | BR6: ='Tenant Payment info'!X6 | BS6: ='Tenant Payment info'!Y6 | BT6: ='Tenant Payment info'!Z6 | BX6: =PromotionsDiscounts!D6 | BY6: =PromotionsDiscounts!E6 | BZ6: =PromotionsDiscounts!F6 | CA6: =PromotionsDiscounts!G6 | CB6: =PromotionsDiscounts!H6 | CC6: =PromotionsDiscounts!I6 | CD6: =PromotionsDiscounts!J6 | CE6: =PromotionsDiscounts!K6 | CF6: ='Tenants Military Information'!F6 | CG6: ='Tenants Military Information'!G6 | CH6: ='Tenants Military Information'!H6 | CI6: ='Tenants Military Information'!I6 | CJ6: ='Tenants Military Information'!J6 | CK6: ='Tenants Military Information'!K6 | CL6: ='Tenants Military Information'!L6 | CM6: ='Tenants Military Information'!M6 | ... CV6: ='Tenants Military Information'!V6 | CW6: ='Tenants Lien Holder Information'!E6 | CX6: ='Tenants Lien Holder Information'!F6 | CY6: ='Tenants Lien Holder Information'!G6 | CZ6: ='Tenants Lien Holder Information'!H6 | DA6: ='Tenants Lien Holder Information'!I6 | DB6: ='Tenants Lien Holder Information'!J6 | DC6: ='Tenants Lien Holder Information'!K6 | DD6: ='Tenants Lien Holder Information'!L6 | DE6: ='Tenants Lien Holder Information'!M6
D7: ='Space mix'!B7 | E7: ='Space mix'!A7 | F7: ='Space mix'!D7 | G7: ='Space mix'!E7 | H7: ='Space mix'!F7 | I7: ='Space mix'!G7 | K7: ='Space mix'!L7 | L7: ='Space mix'!H7 | M7: ='Space mix'!C7 | N7: ='Space mix'!J7 | O7: ='Space mix'!K7 | Q7: ='Space mix'!M7 | R7: ='Space mix'!I7 | S7: ='Tenant Info'!C7 | T7: ='Tenant Info'!D7 | U7: ='Tenant Info'!E7 | V7: ='Tenant Info'!I7 | W7: ='Tenant Info'!J7 | X7: ='Tenant Info'!K7 | Y7: ='Tenant Info'!L7 | Z7: ='Tenant Info'!M7 | AA7: ='Tenant Info'!N7 | AB7: ='Tenant Info'!O7 | AC7: ='Tenant Info'!P7 | ... AF7: ='Tenant Info'!S7 | AI7: ='Tenant Info'!H7 | AJ7: ='Tenant Info'!T7 | AK7: ='Tenant Info'!U7 | AL7: ='Tenant Info'!V7 | AM7: ='Tenant Info'!W7 | AN7: ='Tenant Info'!F7 | AP7: ='Tenant Info'!G7 | AR7: ='Tenant Payment info'!H7 | AS7: ='Tenant Payment info'!I7 | AT7: ='Tenant Payment info'!J7 | AU7: ='Tenant Info'!X7 | AV7: ='Tenant Info'!Y7 | AW7: ='Tenant Info'!Z7 | AX7: ='Tenant Info'!AA7 | AY7: ='Tenant Info'!AB7 | AZ7: ='Tenant Info'!AC7 | BA7: ='Tenant Info'!AD7 | BB7: ='Tenant Info'!AE7 | ... BE7: ='Tenant Info'!AH7 | BF7: ='Tenant Payment info'!U7 | BG7: ='Tenant Payment info'!V7 | BH7: ='Tenant Payment info'!M7 | BI7: ='Tenant Payment info'!P7 | BJ7: ='Tenant Payment info'!W7 | BK7: ='Tenant Payment info'!AA7 | BL7: ='Tenant Payment info'!N7 | BM7: ='Tenant Payment info'!O7 | BN7: ='Tenant Payment info'!S7 | BO7: ='Tenant Payment info'!Q7 | BP7: ='Tenant Payment info'!R7 | BQ7: ='Tenant Payment info'!T7 | BR7: ='Tenant Payment info'!X7 | BS7: ='Tenant Payment info'!Y7 | BT7: ='Tenant Payment info'!Z7 | BX7: =PromotionsDiscounts!D7 | BY7: =PromotionsDiscounts!E7 | BZ7: =PromotionsDiscounts!F7 | CA7: =PromotionsDiscounts!G7 | CB7: =PromotionsDiscounts!H7 | CC7: =PromotionsDiscounts!I7 | CD7: =PromotionsDiscounts!J7 | CE7: =PromotionsDiscounts!K7 | CF7: ='Tenants Military Information'!F7 | CG7: ='Tenants Military Information'!G7 | CH7: ='Tenants Military Information'!H7 | CI7: ='Tenants Military Information'!I7 | CJ7: ='Tenants Military Information'!J7 | CK7: ='Tenants Military Information'!K7 | CL7: ='Tenants Military Information'!L7 | CM7: ='Tenants Military Information'!M7 | ... CV7: ='Tenants Military Information'!V7 | CW7: ='Tenants Lien Holder Information'!E7 | CX7: ='Tenants Lien Holder Information'!F7 | CY7: ='Tenants Lien Holder Information'!G7 | CZ7: ='Tenants Lien Holder Information'!H7 | DA7: ='Tenants Lien Holder Information'!I7 | DB7: ='Tenants Lien Holder Information'!J7 | DC7: ='Tenants Lien Holder Information'!K7 | DD7: ='Tenants Lien Holder Information'!L7 | DE7: ='Tenants Lien Holder Information'!M7
D8: ='Space mix'!B8 | E8: ='Space mix'!A8 | F8: ='Space mix'!D8 | G8: ='Space mix'!E8 | H8: ='Space mix'!F8 | I8: ='Space mix'!G8 | K8: ='Space mix'!L8 | L8: ='Space mix'!H8 | M8: ='Space mix'!C8 | N8: ='Space mix'!J8 | O8: ='Space mix'!K8 | Q8: ='Space mix'!M8 | R8: ='Space mix'!I8 | S8: ='Tenant Info'!C8 | T8: ='Tenant Info'!D8 | U8: ='Tenant Info'!E8 | V8: ='Tenant Info'!I8 | W8: ='Tenant Info'!J8 | X8: ='Tenant Info'!K8 | Y8: ='Tenant Info'!L8 | Z8: ='Tenant Info'!M8 | AA8: ='Tenant Info'!N8 | AB8: ='Tenant Info'!O8 | AC8: ='Tenant Info'!P8 | ... AF8: ='Tenant Info'!S8 | AI8: ='Tenant Info'!H8 | AJ8: ='Tenant Info'!T8 | AK8: ='Tenant Info'!U8 | AL8: ='Tenant Info'!V8 | AM8: ='Tenant Info'!W8 | AN8: ='Tenant Info'!F8 | AP8: ='Tenant Info'!G8 | AR8: ='Tenant Payment info'!H8 | AS8: ='Tenant Payment info'!I8 | AT8: ='Tenant Payment info'!J8 | AU8: ='Tenant Info'!X8 | AV8: ='Tenant Info'!Y8 | AW8: ='Tenant Info'!Z8 | AX8: ='Tenant Info'!AA8 | AY8: ='Tenant Info'!AB8 | AZ8: ='Tenant Info'!AC8 | BA8: ='Tenant Info'!AD8 | BB8: ='Tenant Info'!AE8 | ... BE8: ='Tenant Info'!AH8 | BF8: ='Tenant Payment info'!U8 | BG8: ='Tenant Payment info'!V8 | BH8: ='Tenant Payment info'!M8 | BI8: ='Tenant Payment info'!P8 | BJ8: ='Tenant Payment info'!W8 | BK8: ='Tenant Payment info'!AA8 | BL8: ='Tenant Payment info'!N8 | BM8: ='Tenant Payment info'!O8 | BN8: ='Tenant Payment info'!S8 | BO8: ='Tenant Payment info'!Q8 | BP8: ='Tenant Payment info'!R8 | BQ8: ='Tenant Payment info'!T8 | BR8: ='Tenant Payment info'!X8 | BS8: ='Tenant Payment info'!Y8 | BT8: ='Tenant Payment info'!Z8 | BX8: =PromotionsDiscounts!D8 | BY8: =PromotionsDiscounts!E8 | BZ8: =PromotionsDiscounts!F8 | CA8: =PromotionsDiscounts!G8 | CB8: =PromotionsDiscounts!H8 | CC8: =PromotionsDiscounts!I8 | CD8: =PromotionsDiscounts!J8 | CE8: =PromotionsDiscounts!K8 | CF8: ='Tenants Military Information'!F8 | CG8: ='Tenants Military Information'!G8 | CH8: ='Tenants Military Information'!H8 | CI8: ='Tenants Military Information'!I8 | CJ8: ='Tenants Military Information'!J8 | CK8: ='Tenants Military Information'!K8 | CL8: ='Tenants Military Information'!L8 | CM8: ='Tenants Military Information'!M8 | ... CV8: ='Tenants Military Information'!V8 | CW8: ='Tenants Lien Holder Information'!E8 | CX8: ='Tenants Lien Holder Information'!F8 | CY8: ='Tenants Lien Holder Information'!G8 | CZ8: ='Tenants Lien Holder Information'!H8 | DA8: ='Tenants Lien Holder Information'!I8 | DB8: ='Tenants Lien Holder Information'!J8 | DC8: ='Tenants Lien Holder Information'!K8 | DD8: ='Tenants Lien Holder Information'!L8 | DE8: ='Tenants Lien Holder Information'!M8
D9: ='Space mix'!B9 | E9: ='Space mix'!A9 | F9: ='Space mix'!D9 | G9: ='Space mix'!E9 | H9: ='Space mix'!F9 | I9: ='Space mix'!G9 | K9: ='Space mix'!L9 | L9: ='Space mix'!H9 | M9: ='Space mix'!C9 | N9: ='Space mix'!J9 | O9: ='Space mix'!K9 | Q9: ='Space mix'!M9 | R9: ='Space mix'!I9 | S9: ='Tenant Info'!C9 | T9: ='Tenant Info'!D9 | U9: ='Tenant Info'!E9 | V9: ='Tenant Info'!I9 | W9: ='Tenant Info'!J9 | X9: ='Tenant Info'!K9 | Y9: ='Tenant Info'!L9 | Z9: ='Tenant Info'!M9 | AA9: ='Tenant Info'!N9 | AB9: ='Tenant Info'!O9 | AC9: ='Tenant Info'!P9 | ... AF9: ='Tenant Info'!S9 | AI9: ='Tenant Info'!H9 | AJ9: ='Tenant Info'!T9 | AK9: ='Tenant Info'!U9 | AL9: ='Tenant Info'!V9 | AM9: ='Tenant Info'!W9 | AN9: ='Tenant Info'!F9 | AP9: ='Tenant Info'!G9 | AR9: ='Tenant Payment info'!H9 | AS9: ='Tenant Payment info'!I9 | AT9: ='Tenant Payment info'!J9 | AU9: ='Tenant Info'!X9 | AV9: ='Tenant Info'!Y9 | AW9: ='Tenant Info'!Z9 | AX9: ='Tenant Info'!AA9 | AY9: ='Tenant Info'!AB9 | AZ9: ='Tenant Info'!AC9 | BA9: ='Tenant Info'!AD9 | BB9: ='Tenant Info'!AE9 | ... BE9: ='Tenant Info'!AH9 | BF9: ='Tenant Payment info'!U9 | BG9: ='Tenant Payment info'!V9 | BH9: ='Tenant Payment info'!M9 | BI9: ='Tenant Payment info'!P9 | BJ9: ='Tenant Payment info'!W9 | BK9: ='Tenant Payment info'!AA9 | BL9: ='Tenant Payment info'!N9 | BM9: ='Tenant Payment info'!O9 | BN9: ='Tenant Payment info'!S9 | BO9: ='Tenant Payment info'!Q9 | BP9: ='Tenant Payment info'!R9 | BQ9: ='Tenant Payment info'!T9 | BR9: ='Tenant Payment info'!X9 | BS9: ='Tenant Payment info'!Y9 | BT9: ='Tenant Payment info'!Z9 | BX9: =PromotionsDiscounts!D9 | BY9: =PromotionsDiscounts!E9 | BZ9: =PromotionsDiscounts!F9 | CA9: =PromotionsDiscounts!G9 | CB9: =PromotionsDiscounts!H9 | CC9: =PromotionsDiscounts!I9 | CD9: =PromotionsDiscounts!J9 | CE9: =PromotionsDiscounts!K9 | CF9: ='Tenants Military Information'!F9 | CG9: ='Tenants Military Information'!G9 | CH9: ='Tenants Military Information'!H9 | CI9: ='Tenants Military Information'!I9 | CJ9: ='Tenants Military Information'!J9 | CK9: ='Tenants Military Information'!K9 | CL9: ='Tenants Military Information'!L9 | CM9: ='Tenants Military Information'!M9 | ... CV9: ='Tenants Military Information'!V9 | CW9: ='Tenants Lien Holder Information'!E9 | CX9: ='Tenants Lien Holder Information'!F9 | CY9: ='Tenants Lien Holder Information'!G9 | CZ9: ='Tenants Lien Holder Information'!H9 | DA9: ='Tenants Lien Holder Information'!I9 | DB9: ='Tenants Lien Holder Information'!J9 | DC9: ='Tenants Lien Holder Information'!K9 | DD9: ='Tenants Lien Holder Information'!L9 | DE9: ='Tenants Lien Holder Information'!M9
D10: ='Space mix'!B10 | E10: ='Space mix'!A10 | F10: ='Space mix'!D10 | G10: ='Space mix'!E10 | H10: ='Space mix'!F10 | I10: ='Space mix'!G10 | K10: ='Space mix'!L10 | L10: ='Space mix'!H10 | M10: ='Space mix'!C10 | N10: ='Space mix'!J10 | O10: ='Space mix'!K10 | Q10: ='Space mix'!M10 | R10: ='Space mix'!I10 | S10: ='Tenant Info'!C10 | T10: ='Tenant Info'!D10 | U10: ='Tenant Info'!E10 | V10: ='Tenant Info'!I10 | W10: ='Tenant Info'!J10 | X10: ='Tenant Info'!K10 | Y10: ='Tenant Info'!L10 | Z10: ='Tenant Info'!M10 | AA10: ='Tenant Info'!N10 | AB10: ='Tenant Info'!O10 | AC10: ='Tenant Info'!P10 | ... AF10: ='Tenant Info'!S10 | AI10: ='Tenant Info'!H10 | AJ10: ='Tenant Info'!T10 | AK10: ='Tenant Info'!U10 | AL10: ='Tenant Info'!V10 | AM10: ='Tenant Info'!W10 | AN10: ='Tenant Info'!F10 | AP10: ='Tenant Info'!G10 | AR10: ='Tenant Payment info'!H10 | AS10: ='Tenant Payment info'!I10 | AT10: ='Tenant Payment info'!J10 | AU10: ='Tenant Info'!X10 | AV10: ='Tenant Info'!Y10 | AW10: ='Tenant Info'!Z10 | AX10: ='Tenant Info'!AA10 | AY10: ='Tenant Info'!AB10 | AZ10: ='Tenant Info'!AC10 | BA10: ='Tenant Info'!AD10 | BB10: ='Tenant Info'!AE10 | ... BE10: ='Tenant Info'!AH10 | BF10: ='Tenant Payment info'!U10 | BG10: ='Tenant Payment info'!V10 | BH10: ='Tenant Payment info'!M10 | BI10: ='Tenant Payment info'!P10 | BJ10: ='Tenant Payment info'!W10 | BK10: ='Tenant Payment info'!AA10 | BL10: ='Tenant Payment info'!N10 | BM10: ='Tenant Payment info'!O10 | BN10: ='Tenant Payment info'!S10 | BO10: ='Tenant Payment info'!Q10 | BP10: ='Tenant Payment info'!R10 | BQ10: ='Tenant Payment info'!T10 | BR10: ='Tenant Payment info'!X10 | BS10: ='Tenant Payment info'!Y10 | BT10: ='Tenant Payment info'!Z10 | BX10: =PromotionsDiscounts!D10 | BY10: =PromotionsDiscounts!E10 | BZ10: =PromotionsDiscounts!F10 | CA10: =PromotionsDiscounts!G10 | CB10: =PromotionsDiscounts!H10 | CC10: =PromotionsDiscounts!I10 | CD10: =PromotionsDiscounts!J10 | CE10: =PromotionsDiscounts!K10 | CF10: ='Tenants Military Information'!F10 | CG10: ='Tenants Military Information'!G10 | CH10: ='Tenants Military Information'!H10 | CI10: ='Tenants Military Information'!I10 | CJ10: ='Tenants Military Information'!J10 | CK10: ='Tenants Military Information'!K10 | CL10: ='Tenants Military Information'!L10 | CM10: ='Tenants Military Information'!M10 | ... CV10: ='Tenants Military Information'!V10 | CW10: ='Tenants Lien Holder Information'!E10 | CX10: ='Tenants Lien Holder Information'!F10 | CY10: ='Tenants Lien Holder Information'!G10 | CZ10: ='Tenants Lien Holder Information'!H10 | DA10: ='Tenants Lien Holder Information'!I10 | DB10: ='Tenants Lien Holder Information'!J10 | DC10: ='Tenants Lien Holder Information'!K10 | DD10: ='Tenants Lien Holder Information'!L10 | DE10: ='Tenants Lien Holder Information'!M10
D11: ='Space mix'!B11 | E11: ='Space mix'!A11 | F11: ='Space mix'!D11 | G11: ='Space mix'!E11 | H11: ='Space mix'!F11 | I11: ='Space mix'!G11 | K11: ='Space mix'!L11 | L11: ='Space mix'!H11 | M11: ='Space mix'!C11 | N11: ='Space mix'!J11 | O11: ='Space mix'!K11 | Q11: ='Space mix'!M11 | R11: ='Space mix'!I11 | S11: ='Tenant Info'!C11 | T11: ='Tenant Info'!D11 | U11: ='Tenant Info'!E11 | V11: ='Tenant Info'!I11 | W11: ='Tenant Info'!J11 | X11: ='Tenant Info'!K11 | Y11: ='Tenant Info'!L11 | Z11: ='Tenant Info'!M11 | AA11: ='Tenant Info'!N11 | AB11: ='Tenant Info'!O11 | AC11: ='Tenant Info'!P11 | ... AF11: ='Tenant Info'!S11 | AI11: ='Tenant Info'!H11 | AJ11: ='Tenant Info'!T11 | AK11: ='Tenant Info'!U11 | AL11: ='Tenant Info'!V11 | AM11: ='Tenant Info'!W11 | AN11: ='Tenant Info'!F11 | AP11: ='Tenant Info'!G11 | AR11: ='Tenant Payment info'!H11 | AS11: ='Tenant Payment info'!I11 | AT11: ='Tenant Payment info'!J11 | AU11: ='Tenant Info'!X11 | AV11: ='Tenant Info'!Y11 | AW11: ='Tenant Info'!Z11 | AX11: ='Tenant Info'!AA11 | AY11: ='Tenant Info'!AB11 | AZ11: ='Tenant Info'!AC11 | BA11: ='Tenant Info'!AD11 | BB11: ='Tenant Info'!AE11 | ... BE11: ='Tenant Info'!AH11 | BF11: ='Tenant Payment info'!U11 | BG11: ='Tenant Payment info'!V11 | BH11: ='Tenant Payment info'!M11 | BI11: ='Tenant Payment info'!P11 | BJ11: ='Tenant Payment info'!W11 | BK11: ='Tenant Payment info'!AA11 | BL11: ='Tenant Payment info'!N11 | BM11: ='Tenant Payment info'!O11 | BN11: ='Tenant Payment info'!S11 | BO11: ='Tenant Payment info'!Q11 | BP11: ='Tenant Payment info'!R11 | BQ11: ='Tenant Payment info'!T11 | BR11: ='Tenant Payment info'!X11 | BS11: ='Tenant Payment info'!Y11 | BT11: ='Tenant Payment info'!Z11 | BX11: =PromotionsDiscounts!D11 | BY11: =PromotionsDiscounts!E11 | BZ11: =PromotionsDiscounts!F11 | CA11: =PromotionsDiscounts!G11 | CB11: =PromotionsDiscounts!H11 | CC11: =PromotionsDiscounts!I11 | CD11: =PromotionsDiscounts!J11 | CE11: =PromotionsDiscounts!K11 | CF11: ='Tenants Military Information'!F11 | CG11: ='Tenants Military Information'!G11 | CH11: ='Tenants Military Information'!H11 | CI11: ='Tenants Military Information'!I11 | CJ11: ='Tenants Military Information'!J11 | CK11: ='Tenants Military Information'!K11 | CL11: ='Tenants Military Information'!L11 | CM11: ='Tenants Military Information'!M11 | ... CV11: ='Tenants Military Information'!V11 | CW11: ='Tenants Lien Holder Information'!E11 | CX11: ='Tenants Lien Holder Information'!F11 | CY11: ='Tenants Lien Holder Information'!G11 | CZ11: ='Tenants Lien Holder Information'!H11 | DA11: ='Tenants Lien Holder Information'!I11 | DB11: ='Tenants Lien Holder Information'!J11 | DC11: ='Tenants Lien Holder Information'!K11 | DD11: ='Tenants Lien Holder Information'!L11 | DE11: ='Tenants Lien Holder Information'!M11
D12: ='Space mix'!B12 | E12: ='Space mix'!A12 | F12: ='Space mix'!D12 | G12: ='Space mix'!E12 | H12: ='Space mix'!F12 | I12: ='Space mix'!G12 | K12: ='Space mix'!L12 | L12: ='Space mix'!H12 | M12: ='Space mix'!C12 | N12: ='Space mix'!J12 | O12: ='Space mix'!K12 | Q12: ='Space mix'!M12 | R12: ='Space mix'!I12 | S12: ='Tenant Info'!C12 | T12: ='Tenant Info'!D12 | U12: ='Tenant Info'!E12 | V12: ='Tenant Info'!I12 | W12: ='Tenant Info'!J12 | X12: ='Tenant Info'!K12 | Y12: ='Tenant Info'!L12 | Z12: ='Tenant Info'!M12 | AA12: ='Tenant Info'!N12 | AB12: ='Tenant Info'!O12 | AC12: ='Tenant Info'!P12 | ... AF12: ='Tenant Info'!S12 | AI12: ='Tenant Info'!H12 | AJ12: ='Tenant Info'!T12 | AK12: ='Tenant Info'!U12 | AL12: ='Tenant Info'!V12 | AM12: ='Tenant Info'!W12 | AN12: ='Tenant Info'!F12 | AP12: ='Tenant Info'!G12 | AR12: ='Tenant Payment info'!H12 | AS12: ='Tenant Payment info'!I12 | AT12: ='Tenant Payment info'!J12 | AU12: ='Tenant Info'!X12 | AV12: ='Tenant Info'!Y12 | AW12: ='Tenant Info'!Z12 | AX12: ='Tenant Info'!AA12 | AY12: ='Tenant Info'!AB12 | AZ12: ='Tenant Info'!AC12 | BA12: ='Tenant Info'!AD12 | BB12: ='Tenant Info'!AE12 | ... BE12: ='Tenant Info'!AH12 | BF12: ='Tenant Payment info'!U12 | BG12: ='Tenant Payment info'!V12 | BH12: ='Tenant Payment info'!M12 | BI12: ='Tenant Payment info'!P12 | BJ12: ='Tenant Payment info'!W12 | BK12: ='Tenant Payment info'!AA12 | BL12: ='Tenant Payment info'!N12 | BM12: ='Tenant Payment info'!O12 | BN12: ='Tenant Payment info'!S12 | BO12: ='Tenant Payment info'!Q12 | BP12: ='Tenant Payment info'!R12 | BQ12: ='Tenant Payment info'!T12 | BR12: ='Tenant Payment info'!X12 | BS12: ='Tenant Payment info'!Y12 | BT12: ='Tenant Payment info'!Z12 | BX12: =PromotionsDiscounts!D12 | BY12: =PromotionsDiscounts!E12 | BZ12: =PromotionsDiscounts!F12 | CA12: =PromotionsDiscounts!G12 | CB12: =PromotionsDiscounts!H12 | CC12: =PromotionsDiscounts!I12 | CD12: =PromotionsDiscounts!J12 | CE12: =PromotionsDiscounts!K12 | CF12: ='Tenants Military Information'!F12 | CG12: ='Tenants Military Information'!G12 | CH12: ='Tenants Military Information'!H12 | CI12: ='Tenants Military Information'!I12 | CJ12: ='Tenants Military Information'!J12 | CK12: ='Tenants Military Information'!K12 | CL12: ='Tenants Military Information'!L12 | CM12: ='Tenants Military Information'!M12 | ... CV12: ='Tenants Military Information'!V12 | CW12: ='Tenants Lien Holder Information'!E12 | CX12: ='Tenants Lien Holder Information'!F12 | CY12: ='Tenants Lien Holder Information'!G12 | CZ12: ='Tenants Lien Holder Information'!H12 | DA12: ='Tenants Lien Holder Information'!I12 | DB12: ='Tenants Lien Holder Information'!J12 | DC12: ='Tenants Lien Holder Information'!K12 | DD12: ='Tenants Lien Holder Information'!L12 | DE12: ='Tenants Lien Holder Information'!M12
D13: ='Space mix'!B13 | E13: ='Space mix'!A13 | F13: ='Space mix'!D13 | G13: ='Space mix'!E13 | H13: ='Space mix'!F13 | I13: ='Space mix'!G13 | K13: ='Space mix'!L13 | L13: ='Space mix'!H13 | M13: ='Space mix'!C13 | N13: ='Space mix'!J13 | O13: ='Space mix'!K13 | Q13: ='Space mix'!M13 | R13: ='Space mix'!I13 | S13: ='Tenant Info'!C13 | T13: ='Tenant Info'!D13 | U13: ='Tenant Info'!E13 | V13: ='Tenant Info'!I13 | W13: ='Tenant Info'!J13 | X13: ='Tenant Info'!K13 | Y13: ='Tenant Info'!L13 | Z13: ='Tenant Info'!M13 | AA13: ='Tenant Info'!N13 | AB13: ='Tenant Info'!O13 | AC13: ='Tenant Info'!P13 | ... AF13: ='Tenant Info'!S13 | AI13: ='Tenant Info'!H13 | AJ13: ='Tenant Info'!T13 | AK13: ='Tenant Info'!U13 | AL13: ='Tenant Info'!V13 | AM13: ='Tenant Info'!W13 | AN13: ='Tenant Info'!F13 | AP13: ='Tenant Info'!G13 | AR13: ='Tenant Payment info'!H13 | AS13: ='Tenant Payment info'!I13 | AT13: ='Tenant Payment info'!J13 | AU13: ='Tenant Info'!X13 | AV13: ='Tenant Info'!Y13 | AW13: ='Tenant Info'!Z13 | AX13: ='Tenant Info'!AA13 | AY13: ='Tenant Info'!AB13 | AZ13: ='Tenant Info'!AC13 | BA13: ='Tenant Info'!AD13 | BB13: ='Tenant Info'!AE13 | ... BE13: ='Tenant Info'!AH13 | BF13: ='Tenant Payment info'!U13 | BG13: ='Tenant Payment info'!V13 | BH13: ='Tenant Payment info'!M13 | BI13: ='Tenant Payment info'!P13 | BJ13: ='Tenant Payment info'!W13 | BK13: ='Tenant Payment info'!AA13 | BL13: ='Tenant Payment info'!N13 | BM13: ='Tenant Payment info'!O13 | BN13: ='Tenant Payment info'!S13 | BO13: ='Tenant Payment info'!Q13 | BP13: ='Tenant Payment info'!R13 | BQ13: ='Tenant Payment info'!T13 | BR13: ='Tenant Payment info'!X13 | BS13: ='Tenant Payment info'!Y13 | BT13: ='Tenant Payment info'!Z13 | BX13: =PromotionsDiscounts!D13 | BY13: =PromotionsDiscounts!E13 | BZ13: =PromotionsDiscounts!F13 | CA13: =PromotionsDiscounts!G13 | CB13: =PromotionsDiscounts!H13 | CC13: =PromotionsDiscounts!I13 | CD13: =PromotionsDiscounts!J13 | CE13: =PromotionsDiscounts!K13 | CF13: ='Tenants Military Information'!F13 | CG13: ='Tenants Military Information'!G13 | CH13: ='Tenants Military Information'!H13 | CI13: ='Tenants Military Information'!I13 | CJ13: ='Tenants Military Information'!J13 | CK13: ='Tenants Military Information'!K13 | CL13: ='Tenants Military Information'!L13 | CM13: ='Tenants Military Information'!M13 | ... CV13: ='Tenants Military Information'!V13 | CW13: ='Tenants Lien Holder Information'!E13 | CX13: ='Tenants Lien Holder Information'!F13 | CY13: ='Tenants Lien Holder Information'!G13 | CZ13: ='Tenants Lien Holder Information'!H13 | DA13: ='Tenants Lien Holder Information'!I13 | DB13: ='Tenants Lien Holder Information'!J13 | DC13: ='Tenants Lien Holder Information'!K13 | DD13: ='Tenants Lien Holder Information'!L13 | DE13: ='Tenants Lien Holder Information'!M13
D14: ='Space mix'!B14 | E14: ='Space mix'!A14 | F14: ='Space mix'!D14 | G14: ='Space mix'!E14 | H14: ='Space mix'!F14 | I14: ='Space mix'!G14 | K14: ='Space mix'!L14 | L14: ='Space mix'!H14 | M14: ='Space mix'!C14 | N14: ='Space mix'!J14 | O14: ='Space mix'!K14 | Q14: ='Space mix'!M14 | R14: ='Space mix'!I14 | S14: ='Tenant Info'!C14 | T14: ='Tenant Info'!D14 | U14: ='Tenant Info'!E14 | V14: ='Tenant Info'!I14 | W14: ='Tenant Info'!J14 | X14: ='Tenant Info'!K14 | Y14: ='Tenant Info'!L14 | Z14: ='Tenant Info'!M14 | AA14: ='Tenant Info'!N14 | AB14: ='Tenant Info'!O14 | AC14: ='Tenant Info'!P14 | ... AF14: ='Tenant Info'!S14 | AI14: ='Tenant Info'!H14 | AJ14: ='Tenant Info'!T14 | AK14: ='Tenant Info'!U14 | AL14: ='Tenant Info'!V14 | AM14: ='Tenant Info'!W14 | AN14: ='Tenant Info'!F14 | AP14: ='Tenant Info'!G14 | AR14: ='Tenant Payment info'!H14 | AS14: ='Tenant Payment info'!I14 | AT14: ='Tenant Payment info'!J14 | AU14: ='Tenant Info'!X14 | AV14: ='Tenant Info'!Y14 | AW14: ='Tenant Info'!Z14 | AX14: ='Tenant Info'!AA14 | AY14: ='Tenant Info'!AB14 | AZ14: ='Tenant Info'!AC14 | BA14: ='Tenant Info'!AD14 | BB14: ='Tenant Info'!AE14 | ... BE14: ='Tenant Info'!AH14 | BF14: ='Tenant Payment info'!U14 | BG14: ='Tenant Payment info'!V14 | BH14: ='Tenant Payment info'!M14 | BI14: ='Tenant Payment info'!P14 | BJ14: ='Tenant Payment info'!W14 | BK14: ='Tenant Payment info'!AA14 | BL14: ='Tenant Payment info'!N14 | BM14: ='Tenant Payment info'!O14 | BN14: ='Tenant Payment info'!S14 | BO14: ='Tenant Payment info'!Q14 | BP14: ='Tenant Payment info'!R14 | BQ14: ='Tenant Payment info'!T14 | BR14: ='Tenant Payment info'!X14 | BS14: ='Tenant Payment info'!Y14 | BT14: ='Tenant Payment info'!Z14 | BX14: =PromotionsDiscounts!D14 | BY14: =PromotionsDiscounts!E14 | BZ14: =PromotionsDiscounts!F14 | CA14: =PromotionsDiscounts!G14 | CB14: =PromotionsDiscounts!H14 | CC14: =PromotionsDiscounts!I14 | CD14: =PromotionsDiscounts!J14 | CE14: =PromotionsDiscounts!K14 | CF14: ='Tenants Military Information'!F14 | CG14: ='Tenants Military Information'!G14 | CH14: ='Tenants Military Information'!H14 | CI14: ='Tenants Military Information'!I14 | CJ14: ='Tenants Military Information'!J14 | CK14: ='Tenants Military Information'!K14 | CL14: ='Tenants Military Information'!L14 | CM14: ='Tenants Military Information'!M14 | ... CV14: ='Tenants Military Information'!V14 | CW14: ='Tenants Lien Holder Information'!E14 | CX14: ='Tenants Lien Holder Information'!F14 | CY14: ='Tenants Lien Holder Information'!G14 | CZ14: ='Tenants Lien Holder Information'!H14 | DA14: ='Tenants Lien Holder Information'!I14 | DB14: ='Tenants Lien Holder Information'!J14 | DC14: ='Tenants Lien Holder Information'!K14 | DD14: ='Tenants Lien Holder Information'!L14 | DE14: ='Tenants Lien Holder Information'!M14
D15: ='Space mix'!B15 | E15: ='Space mix'!A15 | F15: ='Space mix'!D15 | G15: ='Space mix'!E15 | H15: ='Space mix'!F15 | I15: ='Space mix'!G15 | K15: ='Space mix'!L15 | L15: ='Space mix'!H15 | M15: ='Space mix'!C15 | N15: ='Space mix'!J15 | O15: ='Space mix'!K15 | Q15: ='Space mix'!M15 | R15: ='Space mix'!I15 | S15: ='Tenant Info'!C15 | T15: ='Tenant Info'!D15 | U15: ='Tenant Info'!E15 | V15: ='Tenant Info'!I15 | W15: ='Tenant Info'!J15 | X15: ='Tenant Info'!K15 | Y15: ='Tenant Info'!L15 | Z15: ='Tenant Info'!M15 | AA15: ='Tenant Info'!N15 | AB15: ='Tenant Info'!O15 | AC15: ='Tenant Info'!P15 | ... AF15: ='Tenant Info'!S15 | AI15: ='Tenant Info'!H15 | AJ15: ='Tenant Info'!T15 | AK15: ='Tenant Info'!U15 | AL15: ='Tenant Info'!V15 | AM15: ='Tenant Info'!W15 | AN15: ='Tenant Info'!F15 | AP15: ='Tenant Info'!G15 | AR15: ='Tenant Payment info'!H15 | AS15: ='Tenant Payment info'!I15 | AT15: ='Tenant Payment info'!J15 | AU15: ='Tenant Info'!X15 | AV15: ='Tenant Info'!Y15 | AW15: ='Tenant Info'!Z15 | AX15: ='Tenant Info'!AA15 | AY15: ='Tenant Info'!AB15 | AZ15: ='Tenant Info'!AC15 | BA15: ='Tenant Info'!AD15 | BB15: ='Tenant Info'!AE15 | ... BE15: ='Tenant Info'!AH15 | BF15: ='Tenant Payment info'!U15 | BG15: ='Tenant Payment info'!V15 | BH15: ='Tenant Payment info'!M15 | BI15: ='Tenant Payment info'!P15 | BJ15: ='Tenant Payment info'!W15 | BK15: ='Tenant Payment info'!AA15 | BL15: ='Tenant Payment info'!N15 | BM15: ='Tenant Payment info'!O15 | BN15: ='Tenant Payment info'!S15 | BO15: ='Tenant Payment info'!Q15 | BP15: ='Tenant Payment info'!R15 | BQ15: ='Tenant Payment info'!T15 | BR15: ='Tenant Payment info'!X15 | BS15: ='Tenant Payment info'!Y15 | BT15: ='Tenant Payment info'!Z15 | BX15: =PromotionsDiscounts!D15 | BY15: =PromotionsDiscounts!E15 | BZ15: =PromotionsDiscounts!F15 | CA15: =PromotionsDiscounts!G15 | CB15: =PromotionsDiscounts!H15 | CC15: =PromotionsDiscounts!I15 | CD15: =PromotionsDiscounts!J15 | CE15: =PromotionsDiscounts!K15 | CF15: ='Tenants Military Information'!F15 | CG15: ='Tenants Military Information'!G15 | CH15: ='Tenants Military Information'!H15 | CI15: ='Tenants Military Information'!I15 | CJ15: ='Tenants Military Information'!J15 | CK15: ='Tenants Military Information'!K15 | CL15: ='Tenants Military Information'!L15 | CM15: ='Tenants Military Information'!M15 | ... CV15: ='Tenants Military Information'!V15 | CW15: ='Tenants Lien Holder Information'!E15 | CX15: ='Tenants Lien Holder Information'!F15 | CY15: ='Tenants Lien Holder Information'!G15 | CZ15: ='Tenants Lien Holder Information'!H15 | DA15: ='Tenants Lien Holder Information'!I15 | DB15: ='Tenants Lien Holder Information'!J15 | DC15: ='Tenants Lien Holder Information'!K15 | DD15: ='Tenants Lien Holder Information'!L15 | DE15: ='Tenants Lien Holder Information'!M15
... D738: ='Space mix'!B738 | E738: ='Space mix'!A738 | F738: ='Space mix'!D738 | G738: ='Space mix'!E738 | H738: ='Space mix'!F738 | I738: ='Space mix'!G738 | K738: ='Space mix'!L738 | L738: ='Space mix'!H738 | M738: ='Space mix'!C738 | N738: ='Space mix'!J738 | O738: ='Space mix'!K738 | Q738: ='Space mix'!M738 | R738: ='Space mix'!I738 | S738: ='Tenant Info'!C738 | T738: ='Tenant Info'!D738 | U738: ='Tenant Info'!E738 | V738: ='Tenant Info'!I738 | W738: ='Tenant Info'!J738 | X738: ='Tenant Info'!K738 | Y738: ='Tenant Info'!L738 | Z738: ='Tenant Info'!M738 | AA738: ='Tenant Info'!N738 | AB738: ='Tenant Info'!O738 | AC738: ='Tenant Info'!P738 | ... AF738: ='Tenant Info'!S738 | AI738: ='Tenant Info'!H738 | AJ738: ='Tenant Info'!T738 | AK738: ='Tenant Info'!U738 | AL738: ='Tenant Info'!V738 | AM738: ='Tenant Info'!W738 | AN738: ='Tenant Info'!F738 | AP738: ='Tenant Info'!G738 | AR738: ='Tenant Payment info'!H738 | AS738: ='Tenant Payment info'!I738 | AT738: ='Tenant Payment info'!J738 | AU738: ='Tenant Info'!X738 | AV738: ='Tenant Info'!Y738 | AW738: ='Tenant Info'!Z738 | AX738: ='Tenant Info'!AA738 | AY738: ='Tenant Info'!AB738 | AZ738: ='Tenant Info'!AC738 | BA738: ='Tenant Info'!AD738 | BB738: ='Tenant Info'!AE738 | ... BE738: ='Tenant Info'!AH738 | BF738: ='Tenant Payment info'!U738 | BG738: ='Tenant Payment info'!V738 | BH738: ='Tenant Payment info'!M738 | BI738: ='Tenant Payment info'!P738 | BJ738: ='Tenant Payment info'!W738 | BK738: ='Tenant Payment info'!AA738 | BL738: ='Tenant Payment info'!N738 | BM738: ='Tenant Payment info'!O738 | BN738: ='Tenant Payment info'!S738 | BO738: ='Tenant Payment info'!Q738 | BP738: ='Tenant Payment info'!R738 | BQ738: ='Tenant Payment info'!T738 | BR738: ='Tenant Payment info'!X738 | BS738: ='Tenant Payment info'!Y738 | BT738: ='Tenant Payment info'!Z738 | BX738: =PromotionsDiscounts!D738 | BY738: =PromotionsDiscounts!E738 | BZ738: =PromotionsDiscounts!F738 | CA738: =PromotionsDiscounts!G738 | CB738: =PromotionsDiscounts!H738 | CC738: =PromotionsDiscounts!I738 | CD738: =PromotionsDiscounts!J738 | CE738: =PromotionsDiscounts!K738 | CF738: ='Tenants Military Information'!F738 | CG738: ='Tenants Military Information'!G738 | CH738: ='Tenants Military Information'!H738 | CI738: ='Tenants Military Information'!I738 | CJ738: ='Tenants Military Information'!J738 | CK738: ='Tenants Military Information'!K738 | CL738: ='Tenants Military Information'!L738 | CM738: ='Tenants Military Information'!M738 | ... CV738: ='Tenants Military Information'!V738 | CW738: ='Tenants Lien Holder Information'!E738 | CX738: ='Tenants Lien Holder Information'!F738 | CY738: ='Tenants Lien Holder Information'!G738 | CZ738: ='Tenants Lien Holder Information'!H738 | DA738: ='Tenants Lien Holder Information'!I738 | DB738: ='Tenants Lien Holder Information'!J738 | DC738: ='Tenants Lien Holder Information'!K738 | DD738: ='Tenants Lien Holder Information'!L738 | DE738: ='Tenants Lien Holder Information'!M738
E739: ='Space mix'!A739 | F739: ='Space mix'!D739 | G739: ='Space mix'!E739 | H739: ='Space mix'!F739 | I739: ='Space mix'!G739 | K739: ='Space mix'!L739 | L739: ='Space mix'!H739 | M739: ='Space mix'!C739 | N739: ='Space mix'!J739 | O739: ='Space mix'!K739 | Q739: ='Space mix'!M739 | R739: ='Space mix'!I739 | S739: ='Tenant Info'!C739 | T739: ='Tenant Info'!D739 | U739: ='Tenant Info'!E739 | V739: ='Tenant Info'!I739 | W739: ='Tenant Info'!J739 | X739: ='Tenant Info'!K739 | Y739: ='Tenant Info'!L739 | Z739: ='Tenant Info'!M739 | AA739: ='Tenant Info'!N739 | AB739: ='Tenant Info'!O739 | AC739: ='Tenant Info'!P739 | ... AF739: ='Tenant Info'!S739 | AI739: ='Tenant Info'!H739 | AJ739: ='Tenant Info'!T739 | AK739: ='Tenant Info'!U739 | AL739: ='Tenant Info'!V739 | AM739: ='Tenant Info'!W739 | AN739: ='Tenant Info'!F739 | AP739: ='Tenant Info'!G739 | AR739: ='Tenant Payment info'!H739 | AS739: ='Tenant Payment info'!I739 | AT739: ='Tenant Payment info'!J739 | AU739: ='Tenant Info'!X739 | AV739: ='Tenant Info'!Y739 | AW739: ='Tenant Info'!Z739 | AX739: ='Tenant Info'!AA739 | AY739: ='Tenant Info'!AB739 | AZ739: ='Tenant Info'!AC739 | BA739: ='Tenant Info'!AD739 | BB739: ='Tenant Info'!AE739 | ... BE739: ='Tenant Info'!AH739 | BF739: ='Tenant Payment info'!U739 | BG739: ='Tenant Payment info'!V739 | BH739: ='Tenant Payment info'!M739 | BI739: ='Tenant Payment info'!P739 | BJ739: ='Tenant Payment info'!W739 | BK739: ='Tenant Payment info'!AA739 | BL739: ='Tenant Payment info'!N739 | BM739: ='Tenant Payment info'!O739 | BN739: ='Tenant Payment info'!S739 | BO739: ='Tenant Payment info'!Q739 | BP739: ='Tenant Payment info'!R739 | BQ739: ='Tenant Payment info'!T739 | BR739: ='Tenant Payment info'!X739 | BS739: ='Tenant Payment info'!Y739 | BT739: ='Tenant Payment info'!Z739 | BX739: =PromotionsDiscounts!D739 | BY739: =PromotionsDiscounts!E739 | BZ739: =PromotionsDiscounts!F739 | CA739: =PromotionsDiscounts!G739 | CB739: =PromotionsDiscounts!H739 | CC739: =PromotionsDiscounts!I739 | CD739: =PromotionsDiscounts!J739 | CE739: =PromotionsDiscounts!K739 | CF739: ='Tenants Military Information'!F739 | CG739: ='Tenants Military Information'!G739 | CH739: ='Tenants Military Information'!H739 | CI739: ='Tenants Military Information'!I739 | CJ739: ='Tenants Military Information'!J739 | CK739: ='Tenants Military Information'!K739 | CL739: ='Tenants Military Information'!L739 | CM739: ='Tenants Military Information'!M739 | ... CV739: ='Tenants Military Information'!V739 | CW739: ='Tenants Lien Holder Information'!E739 | CX739: ='Tenants Lien Holder Information'!F739 | CY739: ='Tenants Lien Holder Information'!G739 | CZ739: ='Tenants Lien Holder Information'!H739 | DA739: ='Tenants Lien Holder Information'!I739 | DB739: ='Tenants Lien Holder Information'!J739 | DC739: ='Tenants Lien Holder Information'!K739 | DD739: ='Tenants Lien Holder Information'!L739 | DE739: ='Tenants Lien Holder Information'!M739
E740: ='Space mix'!A740 | F740: ='Space mix'!D740 | G740: ='Space mix'!E740 | H740: ='Space mix'!F740 | I740: ='Space mix'!G740 | K740: ='Space mix'!L740 | L740: ='Space mix'!H740 | M740: ='Space mix'!C740 | N740: ='Space mix'!J740 | O740: ='Space mix'!K740 | Q740: ='Space mix'!M740 | R740: ='Space mix'!I740 | S740: ='Tenant Info'!C740 | T740: ='Tenant Info'!D740 | U740: ='Tenant Info'!E740 | V740: ='Tenant Info'!I740 | W740: ='Tenant Info'!J740 | X740: ='Tenant Info'!K740 | Y740: ='Tenant Info'!L740 | Z740: ='Tenant Info'!M740 | AA740: ='Tenant Info'!N740 | AB740: ='Tenant Info'!O740 | AC740: ='Tenant Info'!P740 | ... AF740: ='Tenant Info'!S740 | AI740: ='Tenant Info'!H740 | AJ740: ='Tenant Info'!T740 | AK740: ='Tenant Info'!U740 | AL740: ='Tenant Info'!V740 | AM740: ='Tenant Info'!W740 | AN740: ='Tenant Info'!F740 | AP740: ='Tenant Info'!G740 | AR740: ='Tenant Payment info'!H740 | AS740: ='Tenant Payment info'!I740 | AT740: ='Tenant Payment info'!J740 | AU740: ='Tenant Info'!X740 | AV740: ='Tenant Info'!Y740 | AW740: ='Tenant Info'!Z740 | AX740: ='Tenant Info'!AA740 | AY740: ='Tenant Info'!AB740 | AZ740: ='Tenant Info'!AC740 | BA740: ='Tenant Info'!AD740 | BB740: ='Tenant Info'!AE740 | ... BE740: ='Tenant Info'!AH740 | BF740: ='Tenant Payment info'!U740 | BG740: ='Tenant Payment info'!V740 | BH740: ='Tenant Payment info'!M740 | BI740: ='Tenant Payment info'!P740 | BJ740: ='Tenant Payment info'!W740 | BK740: ='Tenant Payment info'!AA740 | BL740: ='Tenant Payment info'!N740 | BM740: ='Tenant Payment info'!O740 | BN740: ='Tenant Payment info'!S740 | BO740: ='Tenant Payment info'!Q740 | BP740: ='Tenant Payment info'!R740 | BQ740: ='Tenant Payment info'!T740 | BR740: ='Tenant Payment info'!X740 | BS740: ='Tenant Payment info'!Y740 | BT740: ='Tenant Payment info'!Z740 | BX740: =PromotionsDiscounts!D740 | BY740: =PromotionsDiscounts!E740 | BZ740: =PromotionsDiscounts!F740 | CA740: =PromotionsDiscounts!G740 | CB740: =PromotionsDiscounts!H740 | CC740: =PromotionsDiscounts!I740 | CD740: =PromotionsDiscounts!J740 | CE740: =PromotionsDiscounts!K740 | CF740: ='Tenants Military Information'!F740 | CG740: ='Tenants Military Information'!G740 | CH740: ='Tenants Military Information'!H740 | CI740: ='Tenants Military Information'!I740 | CJ740: ='Tenants Military Information'!J740 | CK740: ='Tenants Military Information'!K740 | CL740: ='Tenants Military Information'!L740 | CM740: ='Tenants Military Information'!M740 | ... CV740: ='Tenants Military Information'!V740 | CW740: ='Tenants Lien Holder Information'!E740 | CX740: ='Tenants Lien Holder Information'!F740 | CY740: ='Tenants Lien Holder Information'!G740 | CZ740: ='Tenants Lien Holder Information'!H740 | DA740: ='Tenants Lien Holder Information'!I740 | DB740: ='Tenants Lien Holder Information'!J740 | DC740: ='Tenants Lien Holder Information'!K740 | DD740: ='Tenants Lien Holder Information'!L740 | DE740: ='Tenants Lien Holder Information'!M740
E741: ='Space mix'!A741 | F741: ='Space mix'!D741 | G741: ='Space mix'!E741 | H741: ='Space mix'!F741 | I741: ='Space mix'!G741 | K741: ='Space mix'!L741 | L741: ='Space mix'!H741 | M741: ='Space mix'!C741 | N741: ='Space mix'!J741 | O741: ='Space mix'!K741 | Q741: ='Space mix'!M741 | R741: ='Space mix'!I741 | S741: ='Tenant Info'!C741 | T741: ='Tenant Info'!D741 | U741: ='Tenant Info'!E741 | V741: ='Tenant Info'!I741 | W741: ='Tenant Info'!J741 | X741: ='Tenant Info'!K741 | Y741: ='Tenant Info'!L741 | Z741: ='Tenant Info'!M741 | AA741: ='Tenant Info'!N741 | AB741: ='Tenant Info'!O741 | AC741: ='Tenant Info'!P741 | ... AF741: ='Tenant Info'!S741 | AI741: ='Tenant Info'!H741 | AJ741: ='Tenant Info'!T741 | AK741: ='Tenant Info'!U741 | AL741: ='Tenant Info'!V741 | AM741: ='Tenant Info'!W741 | AN741: ='Tenant Info'!F741 | AP741: ='Tenant Info'!G741 | AR741: ='Tenant Payment info'!H741 | AS741: ='Tenant Payment info'!I741 | AT741: ='Tenant Payment info'!J741 | AU741: ='Tenant Info'!X741 | AV741: ='Tenant Info'!Y741 | AW741: ='Tenant Info'!Z741 | AX741: ='Tenant Info'!AA741 | AY741: ='Tenant Info'!AB741 | AZ741: ='Tenant Info'!AC741 | BA741: ='Tenant Info'!AD741 | BB741: ='Tenant Info'!AE741 | ... BE741: ='Tenant Info'!AH741 | BF741: ='Tenant Payment info'!U741 | BG741: ='Tenant Payment info'!V741 | BH741: ='Tenant Payment info'!M741 | BI741: ='Tenant Payment info'!P741 | BJ741: ='Tenant Payment info'!W741 | BK741: ='Tenant Payment info'!AA741 | BL741: ='Tenant Payment info'!N741 | BM741: ='Tenant Payment info'!O741 | BN741: ='Tenant Payment info'!S741 | BO741: ='Tenant Payment info'!Q741 | BP741: ='Tenant Payment info'!R741 | BQ741: ='Tenant Payment info'!T741 | BR741: ='Tenant Payment info'!X741 | BS741: ='Tenant Payment info'!Y741 | BT741: ='Tenant Payment info'!Z741 | BX741: =PromotionsDiscounts!D741 | BY741: =PromotionsDiscounts!E741 | BZ741: =PromotionsDiscounts!F741 | CA741: =PromotionsDiscounts!G741 | CB741: =PromotionsDiscounts!H741 | CC741: =PromotionsDiscounts!I741 | CD741: =PromotionsDiscounts!J741 | CE741: =PromotionsDiscounts!K741 | CF741: ='Tenants Military Information'!F741 | CG741: ='Tenants Military Information'!G741 | CH741: ='Tenants Military Information'!H741 | CI741: ='Tenants Military Information'!I741 | CJ741: ='Tenants Military Information'!J741 | CK741: ='Tenants Military Information'!K741 | CL741: ='Tenants Military Information'!L741 | CM741: ='Tenants Military Information'!M741 | ... CV741: ='Tenants Military Information'!V741 | CW741: ='Tenants Lien Holder Information'!E741 | CX741: ='Tenants Lien Holder Information'!F741 | CY741: ='Tenants Lien Holder Information'!G741 | CZ741: ='Tenants Lien Holder Information'!H741 | DA741: ='Tenants Lien Holder Information'!I741 | DB741: ='Tenants Lien Holder Information'!J741 | DC741: ='Tenants Lien Holder Information'!K741 | DD741: ='Tenants Lien Holder Information'!L741 | DE741: ='Tenants Lien Holder Information'!M741
E742: ='Space mix'!A742 | F742: ='Space mix'!D742 | G742: ='Space mix'!E742 | H742: ='Space mix'!F742 | I742: ='Space mix'!G742 | K742: ='Space mix'!L742 | L742: ='Space mix'!H742 | M742: ='Space mix'!C742 | N742: ='Space mix'!J742 | O742: ='Space mix'!K742 | Q742: ='Space mix'!M742 | R742: ='Space mix'!I742 | S742: ='Tenant Info'!C742 | T742: ='Tenant Info'!D742 | U742: ='Tenant Info'!E742 | V742: ='Tenant Info'!I742 | W742: ='Tenant Info'!J742 | X742: ='Tenant Info'!K742 | Y742: ='Tenant Info'!L742 | Z742: ='Tenant Info'!M742 | AA742: ='Tenant Info'!N742 | AB742: ='Tenant Info'!O742 | AC742: ='Tenant Info'!P742 | ... AF742: ='Tenant Info'!S742 | AI742: ='Tenant Info'!H742 | AJ742: ='Tenant Info'!T742 | AK742: ='Tenant Info'!U742 | AL742: ='Tenant Info'!V742 | AM742: ='Tenant Info'!W742 | AN742: ='Tenant Info'!F742 | AP742: ='Tenant Info'!G742 | AR742: ='Tenant Payment info'!H742 | AS742: ='Tenant Payment info'!I742 | AT742: ='Tenant Payment info'!J742 | AU742: ='Tenant Info'!X742 | AV742: ='Tenant Info'!Y742 | AW742: ='Tenant Info'!Z742 | AX742: ='Tenant Info'!AA742 | AY742: ='Tenant Info'!AB742 | AZ742: ='Tenant Info'!AC742 | BA742: ='Tenant Info'!AD742 | BB742: ='Tenant Info'!AE742 | ... BE742: ='Tenant Info'!AH742 | BF742: ='Tenant Payment info'!U742 | BG742: ='Tenant Payment info'!V742 | BH742: ='Tenant Payment info'!M742 | BI742: ='Tenant Payment info'!P742 | BJ742: ='Tenant Payment info'!W742 | BK742: ='Tenant Payment info'!AA742 | BL742: ='Tenant Payment info'!N742 | BM742: ='Tenant Payment info'!O742 | BN742: ='Tenant Payment info'!S742 | BO742: ='Tenant Payment info'!Q742 | BP742: ='Tenant Payment info'!R742 | BQ742: ='Tenant Payment info'!T742 | BR742: ='Tenant Payment info'!X742 | BS742: ='Tenant Payment info'!Y742 | BT742: ='Tenant Payment info'!Z742 | BX742: =PromotionsDiscounts!D742 | BY742: =PromotionsDiscounts!E742 | BZ742: =PromotionsDiscounts!F742 | CA742: =PromotionsDiscounts!G742 | CB742: =PromotionsDiscounts!H742 | CC742: =PromotionsDiscounts!I742 | CD742: =PromotionsDiscounts!J742 | CE742: =PromotionsDiscounts!K742 | CF742: ='Tenants Military Information'!F742 | CG742: ='Tenants Military Information'!G742 | CH742: ='Tenants Military Information'!H742 | CI742: ='Tenants Military Information'!I742 | CJ742: ='Tenants Military Information'!J742 | CK742: ='Tenants Military Information'!K742 | CL742: ='Tenants Military Information'!L742 | CM742: ='Tenants Military Information'!M742 | ... CV742: ='Tenants Military Information'!V742 | CW742: ='Tenants Lien Holder Information'!E742 | CX742: ='Tenants Lien Holder Information'!F742 | CY742: ='Tenants Lien Holder Information'!G742 | CZ742: ='Tenants Lien Holder Information'!H742 | DA742: ='Tenants Lien Holder Information'!I742 | DB742: ='Tenants Lien Holder Information'!J742 | DC742: ='Tenants Lien Holder Information'!K742 | DD742: ='Tenants Lien Holder Information'!L742 | DE742: ='Tenants Lien Holder Information'!M742
E743: ='Space mix'!A743 | F743: ='Space mix'!D743 | G743: ='Space mix'!E743 | H743: ='Space mix'!F743 | I743: ='Space mix'!G743 | K743: ='Space mix'!L743 | L743: ='Space mix'!H743 | M743: ='Space mix'!C743 | N743: ='Space mix'!J743 | O743: ='Space mix'!K743 | Q743: ='Space mix'!M743 | R743: ='Space mix'!I743 | S743: ='Tenant Info'!C743 | T743: ='Tenant Info'!D743 | U743: ='Tenant Info'!E743 | V743: ='Tenant Info'!I743 | W743: ='Tenant Info'!J743 | X743: ='Tenant Info'!K743 | Y743: ='Tenant Info'!L743 | Z743: ='Tenant Info'!M743 | AA743: ='Tenant Info'!N743 | AB743: ='Tenant Info'!O743 | AC743: ='Tenant Info'!P743 | ... AF743: ='Tenant Info'!S743 | AI743: ='Tenant Info'!H743 | AJ743: ='Tenant Info'!T743 | AK743: ='Tenant Info'!U743 | AL743: ='Tenant Info'!V743 | AM743: ='Tenant Info'!W743 | AN743: ='Tenant Info'!F743 | AP743: ='Tenant Info'!G743 | AR743: ='Tenant Payment info'!H743 | AS743: ='Tenant Payment info'!I743 | AT743: ='Tenant Payment info'!J743 | AU743: ='Tenant Info'!X743 | AV743: ='Tenant Info'!Y743 | AW743: ='Tenant Info'!Z743 | AX743: ='Tenant Info'!AA743 | AY743: ='Tenant Info'!AB743 | AZ743: ='Tenant Info'!AC743 | BA743: ='Tenant Info'!AD743 | BB743: ='Tenant Info'!AE743 | ... BE743: ='Tenant Info'!AH743 | BF743: ='Tenant Payment info'!U743 | BG743: ='Tenant Payment info'!V743 | BH743: ='Tenant Payment info'!M743 | BI743: ='Tenant Payment info'!P743 | BJ743: ='Tenant Payment info'!W743 | BK743: ='Tenant Payment info'!AA743 | BL743: ='Tenant Payment info'!N743 | BM743: ='Tenant Payment info'!O743 | BN743: ='Tenant Payment info'!S743 | BO743: ='Tenant Payment info'!Q743 | BP743: ='Tenant Payment info'!R743 | BQ743: ='Tenant Payment info'!T743 | BR743: ='Tenant Payment info'!X743 | BS743: ='Tenant Payment info'!Y743 | BT743: ='Tenant Payment info'!Z743 | BX743: =PromotionsDiscounts!D743 | BY743: =PromotionsDiscounts!E743 | BZ743: =PromotionsDiscounts!F743 | CA743: =PromotionsDiscounts!G743 | CB743: =PromotionsDiscounts!H743 | CC743: =PromotionsDiscounts!I743 | CD743: =PromotionsDiscounts!J743 | CE743: =PromotionsDiscounts!K743 | CF743: ='Tenants Military Information'!F743 | CG743: ='Tenants Military Information'!G743 | CH743: ='Tenants Military Information'!H743 | CI743: ='Tenants Military Information'!I743 | CJ743: ='Tenants Military Information'!J743 | CK743: ='Tenants Military Information'!K743 | CL743: ='Tenants Military Information'!L743 | CM743: ='Tenants Military Information'!M743 | ... CV743: ='Tenants Military Information'!V743 | CW743: ='Tenants Lien Holder Information'!E743 | CX743: ='Tenants Lien Holder Information'!F743 | CY743: ='Tenants Lien Holder Information'!G743 | CZ743: ='Tenants Lien Holder Information'!H743 | DA743: ='Tenants Lien Holder Information'!I743 | DB743: ='Tenants Lien Holder Information'!J743 | DC743: ='Tenants Lien Holder Information'!K743 | DD743: ='Tenants Lien Holder Information'!L743 | DE743: ='Tenants Lien Holder Information'!M743
E744: ='Space mix'!A744 | F744: ='Space mix'!D744 | G744: ='Space mix'!E744 | H744: ='Space mix'!F744 | I744: ='Space mix'!G744 | K744: ='Space mix'!L744 | L744: ='Space mix'!H744 | M744: ='Space mix'!C744 | N744: ='Space mix'!J744 | O744: ='Space mix'!K744 | Q744: ='Space mix'!M744 | R744: ='Space mix'!I744 | S744: ='Tenant Info'!C744 | T744: ='Tenant Info'!D744 | U744: ='Tenant Info'!E744 | V744: ='Tenant Info'!I744 | W744: ='Tenant Info'!J744 | X744: ='Tenant Info'!K744 | Y744: ='Tenant Info'!L744 | Z744: ='Tenant Info'!M744 | AA744: ='Tenant Info'!N744 | AB744: ='Tenant Info'!O744 | AC744: ='Tenant Info'!P744 | ... AF744: ='Tenant Info'!S744 | AI744: ='Tenant Info'!H744 | AJ744: ='Tenant Info'!T744 | AK744: ='Tenant Info'!U744 | AL744: ='Tenant Info'!V744 | AM744: ='Tenant Info'!W744 | AN744: ='Tenant Info'!F744 | AP744: ='Tenant Info'!G744 | AR744: ='Tenant Payment info'!H744 | AS744: ='Tenant Payment info'!I744 | AT744: ='Tenant Payment info'!J744 | AU744: ='Tenant Info'!X744 | AV744: ='Tenant Info'!Y744 | AW744: ='Tenant Info'!Z744 | AX744: ='Tenant Info'!AA744 | AY744: ='Tenant Info'!AB744 | AZ744: ='Tenant Info'!AC744 | BA744: ='Tenant Info'!AD744 | BB744: ='Tenant Info'!AE744 | ... BE744: ='Tenant Info'!AH744 | BF744: ='Tenant Payment info'!U744 | BG744: ='Tenant Payment info'!V744 | BH744: ='Tenant Payment info'!M744 | BI744: ='Tenant Payment info'!P744 | BJ744: ='Tenant Payment info'!W744 | BK744: ='Tenant Payment info'!AA744 | BL744: ='Tenant Payment info'!N744 | BM744: ='Tenant Payment info'!O744 | BN744: ='Tenant Payment info'!S744 | BO744: ='Tenant Payment info'!Q744 | BP744: ='Tenant Payment info'!R744 | BQ744: ='Tenant Payment info'!T744 | BR744: ='Tenant Payment info'!X744 | BS744: ='Tenant Payment info'!Y744 | BT744: ='Tenant Payment info'!Z744 | BX744: =PromotionsDiscounts!D744 | BY744: =PromotionsDiscounts!E744 | BZ744: =PromotionsDiscounts!F744 | CA744: =PromotionsDiscounts!G744 | CB744: =PromotionsDiscounts!H744 | CC744: =PromotionsDiscounts!I744 | CD744: =PromotionsDiscounts!J744 | CE744: =PromotionsDiscounts!K744 | CF744: ='Tenants Military Information'!F744 | CG744: ='Tenants Military Information'!G744 | CH744: ='Tenants Military Information'!H744 | CI744: ='Tenants Military Information'!I744 | CJ744: ='Tenants Military Information'!J744 | CK744: ='Tenants Military Information'!K744 | CL744: ='Tenants Military Information'!L744 | CM744: ='Tenants Military Information'!M744 | ... CV744: ='Tenants Military Information'!V744 | CW744: ='Tenants Lien Holder Information'!E744 | CX744: ='Tenants Lien Holder Information'!F744 | CY744: ='Tenants Lien Holder Information'!G744 | CZ744: ='Tenants Lien Holder Information'!H744 | DA744: ='Tenants Lien Holder Information'!I744 | DB744: ='Tenants Lien Holder Information'!J744 | DC744: ='Tenants Lien Holder Information'!K744 | DD744: ='Tenants Lien Holder Information'!L744 | DE744: ='Tenants Lien Holder Information'!M744
E745: ='Space mix'!A745 | F745: ='Space mix'!D745 | G745: ='Space mix'!E745 | H745: ='Space mix'!F745 | I745: ='Space mix'!G745 | K745: ='Space mix'!L745 | L745: ='Space mix'!H745 | M745: ='Space mix'!C745 | N745: ='Space mix'!J745 | O745: ='Space mix'!K745 | Q745: ='Space mix'!M745 | R745: ='Space mix'!I745 | S745: ='Tenant Info'!C745 | T745: ='Tenant Info'!D745 | U745: ='Tenant Info'!E745 | V745: ='Tenant Info'!I745 | W745: ='Tenant Info'!J745 | X745: ='Tenant Info'!K745 | Y745: ='Tenant Info'!L745 | Z745: ='Tenant Info'!M745 | AA745: ='Tenant Info'!N745 | AB745: ='Tenant Info'!O745 | AC745: ='Tenant Info'!P745 | ... AF745: ='Tenant Info'!S745 | AI745: ='Tenant Info'!H745 | AJ745: ='Tenant Info'!T745 | AK745: ='Tenant Info'!U745 | AL745: ='Tenant Info'!V745 | AM745: ='Tenant Info'!W745 | AN745: ='Tenant Info'!F745 | AP745: ='Tenant Info'!G745 | AR745: ='Tenant Payment info'!H745 | AS745: ='Tenant Payment info'!I745 | AT745: ='Tenant Payment info'!J745 | AU745: ='Tenant Info'!X745 | AV745: ='Tenant Info'!Y745 | AW745: ='Tenant Info'!Z745 | AX745: ='Tenant Info'!AA745 | AY745: ='Tenant Info'!AB745 | AZ745: ='Tenant Info'!AC745 | BA745: ='Tenant Info'!AD745 | BB745: ='Tenant Info'!AE745 | ... BE745: ='Tenant Info'!AH745 | BF745: ='Tenant Payment info'!U745 | BG745: ='Tenant Payment info'!V745 | BH745: ='Tenant Payment info'!M745 | BI745: ='Tenant Payment info'!P745 | BJ745: ='Tenant Payment info'!W745 | BK745: ='Tenant Payment info'!AA745 | BL745: ='Tenant Payment info'!N745 | BM745: ='Tenant Payment info'!O745 | BN745: ='Tenant Payment info'!S745 | BO745: ='Tenant Payment info'!Q745 | BP745: ='Tenant Payment info'!R745 | BQ745: ='Tenant Payment info'!T745 | BR745: ='Tenant Payment info'!X745 | BS745: ='Tenant Payment info'!Y745 | BT745: ='Tenant Payment info'!Z745 | BX745: =PromotionsDiscounts!D745 | BY745: =PromotionsDiscounts!E745 | BZ745: =PromotionsDiscounts!F745 | CA745: =PromotionsDiscounts!G745 | CB745: =PromotionsDiscounts!H745 | CC745: =PromotionsDiscounts!I745 | CD745: =PromotionsDiscounts!J745 | CE745: =PromotionsDiscounts!K745 | CF745: ='Tenants Military Information'!F745 | CG745: ='Tenants Military Information'!G745 | CH745: ='Tenants Military Information'!H745 | CI745: ='Tenants Military Information'!I745 | CJ745: ='Tenants Military Information'!J745 | CK745: ='Tenants Military Information'!K745 | CL745: ='Tenants Military Information'!L745 | CM745: ='Tenants Military Information'!M745 | ... CV745: ='Tenants Military Information'!V745 | CW745: ='Tenants Lien Holder Information'!E745 | CX745: ='Tenants Lien Holder Information'!F745 | CY745: ='Tenants Lien Holder Information'!G745 | CZ745: ='Tenants Lien Holder Information'!H745 | DA745: ='Tenants Lien Holder Information'!I745 | DB745: ='Tenants Lien Holder Information'!J745 | DC745: ='Tenants Lien Holder Information'!K745 | DD745: ='Tenants Lien Holder Information'!L745 | DE745: ='Tenants Lien Holder Information'!M745
E746: ='Space mix'!A746 | F746: ='Space mix'!D746 | G746: ='Space mix'!E746 | H746: ='Space mix'!F746 | I746: ='Space mix'!G746 | K746: ='Space mix'!L746 | L746: ='Space mix'!H746 | M746: ='Space mix'!C746 | N746: ='Space mix'!J746 | O746: ='Space mix'!K746 | Q746: ='Space mix'!M746 | R746: ='Space mix'!I746 | S746: ='Tenant Info'!C746 | T746: ='Tenant Info'!D746 | U746: ='Tenant Info'!E746 | V746: ='Tenant Info'!I746 | W746: ='Tenant Info'!J746 | X746: ='Tenant Info'!K746 | Y746: ='Tenant Info'!L746 | Z746: ='Tenant Info'!M746 | AA746: ='Tenant Info'!N746 | AB746: ='Tenant Info'!O746 | AC746: ='Tenant Info'!P746 | ... AF746: ='Tenant Info'!S746 | AI746: ='Tenant Info'!H746 | AJ746: ='Tenant Info'!T746 | AK746: ='Tenant Info'!U746 | AL746: ='Tenant Info'!V746 | AM746: ='Tenant Info'!W746 | AN746: ='Tenant Info'!F746 | AP746: ='Tenant Info'!G746 | AR746: ='Tenant Payment info'!H746 | AS746: ='Tenant Payment info'!I746 | AT746: ='Tenant Payment info'!J746 | AU746: ='Tenant Info'!X746 | AV746: ='Tenant Info'!Y746 | AW746: ='Tenant Info'!Z746 | AX746: ='Tenant Info'!AA746 | AY746: ='Tenant Info'!AB746 | AZ746: ='Tenant Info'!AC746 | BA746: ='Tenant Info'!AD746 | BB746: ='Tenant Info'!AE746 | ... BE746: ='Tenant Info'!AH746 | BF746: ='Tenant Payment info'!U746 | BG746: ='Tenant Payment info'!V746 | BH746: ='Tenant Payment info'!M746 | BI746: ='Tenant Payment info'!P746 | BJ746: ='Tenant Payment info'!W746 | BK746: ='Tenant Payment info'!AA746 | BL746: ='Tenant Payment info'!N746 | BM746: ='Tenant Payment info'!O746 | BN746: ='Tenant Payment info'!S746 | BO746: ='Tenant Payment info'!Q746 | BP746: ='Tenant Payment info'!R746 | BQ746: ='Tenant Payment info'!T746 | BR746: ='Tenant Payment info'!X746 | BS746: ='Tenant Payment info'!Y746 | BT746: ='Tenant Payment info'!Z746 | BX746: =PromotionsDiscounts!D746 | BY746: =PromotionsDiscounts!E746 | BZ746: =PromotionsDiscounts!F746 | CA746: =PromotionsDiscounts!G746 | CB746: =PromotionsDiscounts!H746 | CC746: =PromotionsDiscounts!I746 | CD746: =PromotionsDiscounts!J746 | CE746: =PromotionsDiscounts!K746 | CF746: ='Tenants Military Information'!F746 | CG746: ='Tenants Military Information'!G746 | CH746: ='Tenants Military Information'!H746 | CI746: ='Tenants Military Information'!I746 | CJ746: ='Tenants Military Information'!J746 | CK746: ='Tenants Military Information'!K746 | CL746: ='Tenants Military Information'!L746 | CM746: ='Tenants Military Information'!M746 | ... CV746: ='Tenants Military Information'!V746 | CW746: ='Tenants Lien Holder Information'!E746 | CX746: ='Tenants Lien Holder Information'!F746 | CY746: ='Tenants Lien Holder Information'!G746 | CZ746: ='Tenants Lien Holder Information'!H746 | DA746: ='Tenants Lien Holder Information'!I746 | DB746: ='Tenants Lien Holder Information'!J746 | DC746: ='Tenants Lien Holder Information'!K746 | DD746: ='Tenants Lien Holder Information'!L746 | DE746: ='Tenants Lien Holder Information'!M746
E747: ='Space mix'!A747 | F747: ='Space mix'!D747 | G747: ='Space mix'!E747 | H747: ='Space mix'!F747 | I747: ='Space mix'!G747 | K747: ='Space mix'!L747 | L747: ='Space mix'!H747 | M747: ='Space mix'!C747 | N747: ='Space mix'!J747 | O747: ='Space mix'!K747 | Q747: ='Space mix'!M747 | R747: ='Space mix'!I747 | S747: ='Tenant Info'!C747 | T747: ='Tenant Info'!D747 | U747: ='Tenant Info'!E747 | V747: ='Tenant Info'!I747 | W747: ='Tenant Info'!J747 | X747: ='Tenant Info'!K747 | Y747: ='Tenant Info'!L747 | Z747: ='Tenant Info'!M747 | AA747: ='Tenant Info'!N747 | AB747: ='Tenant Info'!O747 | AC747: ='Tenant Info'!P747 | ... AF747: ='Tenant Info'!S747 | AI747: ='Tenant Info'!H747 | AJ747: ='Tenant Info'!T747 | AK747: ='Tenant Info'!U747 | AL747: ='Tenant Info'!V747 | AM747: ='Tenant Info'!W747 | AN747: ='Tenant Info'!F747 | AP747: ='Tenant Info'!G747 | AR747: ='Tenant Payment info'!H747 | AS747: ='Tenant Payment info'!I747 | AT747: ='Tenant Payment info'!J747 | AU747: ='Tenant Info'!X747 | AV747: ='Tenant Info'!Y747 | AW747: ='Tenant Info'!Z747 | AX747: ='Tenant Info'!AA747 | AY747: ='Tenant Info'!AB747 | AZ747: ='Tenant Info'!AC747 | BA747: ='Tenant Info'!AD747 | BB747: ='Tenant Info'!AE747 | ... BE747: ='Tenant Info'!AH747 | BF747: ='Tenant Payment info'!U747 | BG747: ='Tenant Payment info'!V747 | BH747: ='Tenant Payment info'!M747 | BI747: ='Tenant Payment info'!P747 | BJ747: ='Tenant Payment info'!W747 | BK747: ='Tenant Payment info'!AA747 | BL747: ='Tenant Payment info'!N747 | BM747: ='Tenant Payment info'!O747 | BN747: ='Tenant Payment info'!S747 | BO747: ='Tenant Payment info'!Q747 | BP747: ='Tenant Payment info'!R747 | BQ747: ='Tenant Payment info'!T747 | BR747: ='Tenant Payment info'!X747 | BS747: ='Tenant Payment info'!Y747 | BT747: ='Tenant Payment info'!Z747 | BX747: =PromotionsDiscounts!D747 | BY747: =PromotionsDiscounts!E747 | BZ747: =PromotionsDiscounts!F747 | CA747: =PromotionsDiscounts!G747 | CB747: =PromotionsDiscounts!H747 | CC747: =PromotionsDiscounts!I747 | CD747: =PromotionsDiscounts!J747 | CE747: =PromotionsDiscounts!K747 | CF747: ='Tenants Military Information'!F747 | CG747: ='Tenants Military Information'!G747 | CH747: ='Tenants Military Information'!H747 | CI747: ='Tenants Military Information'!I747 | CJ747: ='Tenants Military Information'!J747 | CK747: ='Tenants Military Information'!K747 | CL747: ='Tenants Military Information'!L747 | CM747: ='Tenants Military Information'!M747 | ... CV747: ='Tenants Military Information'!V747 | CW747: ='Tenants Lien Holder Information'!E747 | CX747: ='Tenants Lien Holder Information'!F747 | CY747: ='Tenants Lien Holder Information'!G747 | CZ747: ='Tenants Lien Holder Information'!H747 | DA747: ='Tenants Lien Holder Information'!I747 | DB747: ='Tenants Lien Holder Information'!J747 | DC747: ='Tenants Lien Holder Information'!K747 | DD747: ='Tenants Lien Holder Information'!L747 | DE747: ='Tenants Lien Holder Information'!M747
E748: ='Space mix'!A748 | F748: ='Space mix'!D748 | G748: ='Space mix'!E748 | H748: ='Space mix'!F748 | I748: ='Space mix'!G748 | K748: ='Space mix'!L748 | L748: ='Space mix'!H748 | M748: ='Space mix'!C748 | N748: ='Space mix'!J748 | O748: ='Space mix'!K748 | Q748: ='Space mix'!M748 | R748: ='Space mix'!I748 | S748: ='Tenant Info'!C748 | T748: ='Tenant Info'!D748 | U748: ='Tenant Info'!E748 | V748: ='Tenant Info'!I748 | W748: ='Tenant Info'!J748 | X748: ='Tenant Info'!K748 | Y748: ='Tenant Info'!L748 | Z748: ='Tenant Info'!M748 | AA748: ='Tenant Info'!N748 | AB748: ='Tenant Info'!O748 | AC748: ='Tenant Info'!P748 | ... AF748: ='Tenant Info'!S748 | AI748: ='Tenant Info'!H748 | AJ748: ='Tenant Info'!T748 | AK748: ='Tenant Info'!U748 | AL748: ='Tenant Info'!V748 | AM748: ='Tenant Info'!W748 | AN748: ='Tenant Info'!F748 | AP748: ='Tenant Info'!G748 | AR748: ='Tenant Payment info'!H748 | AS748: ='Tenant Payment info'!I748 | AT748: ='Tenant Payment info'!J748 | AU748: ='Tenant Info'!X748 | AV748: ='Tenant Info'!Y748 | AW748: ='Tenant Info'!Z748 | AX748: ='Tenant Info'!AA748 | AY748: ='Tenant Info'!AB748 | AZ748: ='Tenant Info'!AC748 | BA748: ='Tenant Info'!AD748 | BB748: ='Tenant Info'!AE748 | ... BE748: ='Tenant Info'!AH748 | BF748: ='Tenant Payment info'!U748 | BG748: ='Tenant Payment info'!V748 | BH748: ='Tenant Payment info'!M748 | BI748: ='Tenant Payment info'!P748 | BJ748: ='Tenant Payment info'!W748 | BK748: ='Tenant Payment info'!AA748 | BL748: ='Tenant Payment info'!N748 | BM748: ='Tenant Payment info'!O748 | BN748: ='Tenant Payment info'!S748 | BO748: ='Tenant Payment info'!Q748 | BP748: ='Tenant Payment info'!R748 | BQ748: ='Tenant Payment info'!T748 | BR748: ='Tenant Payment info'!X748 | BS748: ='Tenant Payment info'!Y748 | BT748: ='Tenant Payment info'!Z748 | BX748: =PromotionsDiscounts!D748 | BY748: =PromotionsDiscounts!E748 | BZ748: =PromotionsDiscounts!F748 | CA748: =PromotionsDiscounts!G748 | CB748: =PromotionsDiscounts!H748 | CC748: =PromotionsDiscounts!I748 | CD748: =PromotionsDiscounts!J748 | CE748: =PromotionsDiscounts!K748 | CF748: ='Tenants Military Information'!F748 | CG748: ='Tenants Military Information'!G748 | CH748: ='Tenants Military Information'!H748 | CI748: ='Tenants Military Information'!I748 | CJ748: ='Tenants Military Information'!J748 | CK748: ='Tenants Military Information'!K748 | CL748: ='Tenants Military Information'!L748 | CM748: ='Tenants Military Information'!M748 | ... CV748: ='Tenants Military Information'!V748 | CW748: ='Tenants Lien Holder Information'!E748 | CX748: ='Tenants Lien Holder Information'!F748 | CY748: ='Tenants Lien Holder Information'!G748 | CZ748: ='Tenants Lien Holder Information'!H748 | DA748: ='Tenants Lien Holder Information'!I748 | DB748: ='Tenants Lien Holder Information'!J748 | DC748: ='Tenants Lien Holder Information'!K748 | DD748: ='Tenants Lien Holder Information'!L748 | DE748: ='Tenants Lien Holder Information'!M748
E749: ='Space mix'!A749 | F749: ='Space mix'!D749 | G749: ='Space mix'!E749 | H749: ='Space mix'!F749 | I749: ='Space mix'!G749 | K749: ='Space mix'!L749 | L749: ='Space mix'!H749 | M749: ='Space mix'!C749 | N749: ='Space mix'!J749 | O749: ='Space mix'!K749 | Q749: ='Space mix'!M749 | R749: ='Space mix'!I749 | S749: ='Tenant Info'!C749 | T749: ='Tenant Info'!D749 | U749: ='Tenant Info'!E749 | V749: ='Tenant Info'!I749 | W749: ='Tenant Info'!J749 | X749: ='Tenant Info'!K749 | Y749: ='Tenant Info'!L749 | Z749: ='Tenant Info'!M749 | AA749: ='Tenant Info'!N749 | AB749: ='Tenant Info'!O749 | AC749: ='Tenant Info'!P749 | ... AF749: ='Tenant Info'!S749 | AI749: ='Tenant Info'!H749 | AJ749: ='Tenant Info'!T749 | AK749: ='Tenant Info'!U749 | AL749: ='Tenant Info'!V749 | AM749: ='Tenant Info'!W749 | AN749: ='Tenant Info'!F749 | AP749: ='Tenant Info'!G749 | AR749: ='Tenant Payment info'!H749 | AS749: ='Tenant Payment info'!I749 | AT749: ='Tenant Payment info'!J749 | AU749: ='Tenant Info'!X749 | AV749: ='Tenant Info'!Y749 | AW749: ='Tenant Info'!Z749 | AX749: ='Tenant Info'!AA749 | AY749: ='Tenant Info'!AB749 | AZ749: ='Tenant Info'!AC749 | BA749: ='Tenant Info'!AD749 | BB749: ='Tenant Info'!AE749 | ... BE749: ='Tenant Info'!AH749 | BF749: ='Tenant Payment info'!U749 | BG749: ='Tenant Payment info'!V749 | BH749: ='Tenant Payment info'!M749 | BI749: ='Tenant Payment info'!P749 | BJ749: ='Tenant Payment info'!W749 | BK749: ='Tenant Payment info'!AA749 | BL749: ='Tenant Payment info'!N749 | BM749: ='Tenant Payment info'!O749 | BN749: ='Tenant Payment info'!S749 | BO749: ='Tenant Payment info'!Q749 | BP749: ='Tenant Payment info'!R749 | BQ749: ='Tenant Payment info'!T749 | BR749: ='Tenant Payment info'!X749 | BS749: ='Tenant Payment info'!Y749 | BT749: ='Tenant Payment info'!Z749 | BX749: =PromotionsDiscounts!D749 | BY749: =PromotionsDiscounts!E749 | BZ749: =PromotionsDiscounts!F749 | CA749: =PromotionsDiscounts!G749 | CB749: =PromotionsDiscounts!H749 | CC749: =PromotionsDiscounts!I749 | CD749: =PromotionsDiscounts!J749 | CE749: =PromotionsDiscounts!K749 | CF749: ='Tenants Military Information'!F749 | CG749: ='Tenants Military Information'!G749 | CH749: ='Tenants Military Information'!H749 | CI749: ='Tenants Military Information'!I749 | CJ749: ='Tenants Military Information'!J749 | CK749: ='Tenants Military Information'!K749 | CL749: ='Tenants Military Information'!L749 | CM749: ='Tenants Military Information'!M749 | ... CV749: ='Tenants Military Information'!V749 | CW749: ='Tenants Lien Holder Information'!E749 | CX749: ='Tenants Lien Holder Information'!F749 | CY749: ='Tenants Lien Holder Information'!G749 | CZ749: ='Tenants Lien Holder Information'!H749 | DA749: ='Tenants Lien Holder Information'!I749 | DB749: ='Tenants Lien Holder Information'!J749 | DC749: ='Tenants Lien Holder Information'!K749 | DD749: ='Tenants Lien Holder Information'!L749 | DE749: ='Tenants Lien Holder Information'!M749
E750: ='Space mix'!A750 | F750: ='Space mix'!D750 | G750: ='Space mix'!E750 | H750: ='Space mix'!F750 | I750: ='Space mix'!G750 | K750: ='Space mix'!L750 | L750: ='Space mix'!H750 | M750: ='Space mix'!C750 | N750: ='Space mix'!J750 | O750: ='Space mix'!K750 | Q750: ='Space mix'!M750 | R750: ='Space mix'!I750 | S750: ='Tenant Info'!C750 | T750: ='Tenant Info'!D750 | U750: ='Tenant Info'!E750 | V750: ='Tenant Info'!I750 | W750: ='Tenant Info'!J750 | X750: ='Tenant Info'!K750 | Y750: ='Tenant Info'!L750 | Z750: ='Tenant Info'!M750 | AA750: ='Tenant Info'!N750 | AB750: ='Tenant Info'!O750 | AC750: ='Tenant Info'!P750 | ... AF750: ='Tenant Info'!S750 | AI750: ='Tenant Info'!H750 | AJ750: ='Tenant Info'!T750 | AK750: ='Tenant Info'!U750 | AL750: ='Tenant Info'!V750 | AM750: ='Tenant Info'!W750 | AN750: ='Tenant Info'!F750 | AP750: ='Tenant Info'!G750 | AR750: ='Tenant Payment info'!H750 | AS750: ='Tenant Payment info'!I750 | AT750: ='Tenant Payment info'!J750 | AU750: ='Tenant Info'!X750 | AV750: ='Tenant Info'!Y750 | AW750: ='Tenant Info'!Z750 | AX750: ='Tenant Info'!AA750 | AY750: ='Tenant Info'!AB750 | AZ750: ='Tenant Info'!AC750 | BA750: ='Tenant Info'!AD750 | BB750: ='Tenant Info'!AE750 | ... BE750: ='Tenant Info'!AH750 | BF750: ='Tenant Payment info'!U750 | BG750: ='Tenant Payment info'!V750 | BH750: ='Tenant Payment info'!M750 | BI750: ='Tenant Payment info'!P750 | BJ750: ='Tenant Payment info'!W750 | BK750: ='Tenant Payment info'!AA750 | BL750: ='Tenant Payment info'!N750 | BM750: ='Tenant Payment info'!O750 | BN750: ='Tenant Payment info'!S750 | BO750: ='Tenant Payment info'!Q750 | BP750: ='Tenant Payment info'!R750 | BQ750: ='Tenant Payment info'!T750 | BR750: ='Tenant Payment info'!X750 | BS750: ='Tenant Payment info'!Y750 | BT750: ='Tenant Payment info'!Z750 | BX750: =PromotionsDiscounts!D750 | BY750: =PromotionsDiscounts!E750 | BZ750: =PromotionsDiscounts!F750 | CA750: =PromotionsDiscounts!G750 | CB750: =PromotionsDiscounts!H750 | CC750: =PromotionsDiscounts!I750 | CD750: =PromotionsDiscounts!J750 | CE750: =PromotionsDiscounts!K750 | CF750: ='Tenants Military Information'!F750 | CG750: ='Tenants Military Information'!G750 | CH750: ='Tenants Military Information'!H750 | CI750: ='Tenants Military Information'!I750 | CJ750: ='Tenants Military Information'!J750 | CK750: ='Tenants Military Information'!K750 | CL750: ='Tenants Military Information'!L750 | CM750: ='Tenants Military Information'!M750 | ... CV750: ='Tenants Military Information'!V750 | CW750: ='Tenants Lien Holder Information'!E750 | CX750: ='Tenants Lien Holder Information'!F750 | CY750: ='Tenants Lien Holder Information'!G750 | CZ750: ='Tenants Lien Holder Information'!H750 | DA750: ='Tenants Lien Holder Information'!I750 | DB750: ='Tenants Lien Holder Information'!J750 | DC750: ='Tenants Lien Holder Information'!K750 | DD750: ='Tenants Lien Holder Information'!L750 | DE750: ='Tenants Lien Holder Information'!M750
... E1999: ='Space mix'!A1999 | F1999: ='Space mix'!D1999 | G1999: ='Space mix'!E1999 | H1999: ='Space mix'!F1999 | I1999: ='Space mix'!G1999 | K1999: ='Space mix'!L1999 | L1999: ='Space mix'!H1999 | M1999: ='Space mix'!C1999 | N1999: ='Space mix'!J1999 | O1999: ='Space mix'!K1999 | Q1999: ='Space mix'!M1999 | R1999: ='Space mix'!I1999 | S1999: ='Tenant Info'!C1999 | T1999: ='Tenant Info'!D1999 | U1999: ='Tenant Info'!E1999 | V1999: ='Tenant Info'!I1999 | W1999: ='Tenant Info'!J1999 | X1999: ='Tenant Info'!K1999 | Y1999: ='Tenant Info'!L1999 | Z1999: ='Tenant Info'!M1999 | AA1999: ='Tenant Info'!N1999 | AB1999: ='Tenant Info'!O1999 | AC1999: ='Tenant Info'!P1999 | ... AF1999: ='Tenant Info'!S1999 | AI1999: ='Tenant Info'!H1999 | AJ1999: ='Tenant Info'!T1999 | AK1999: ='Tenant Info'!U1999 | AL1999: ='Tenant Info'!V1999 | AM1999: ='Tenant Info'!W1999 | AN1999: ='Tenant Info'!F1999 | AP1999: ='Tenant Info'!G1999 | AR1999: ='Tenant Payment info'!H1999 | AS1999: ='Tenant Payment info'!I1999 | AT1999: ='Tenant Payment info'!J1999 | AU1999: ='Tenant Info'!X1999 | AV1999: ='Tenant Info'!Y1999 | AW1999: ='Tenant Info'!Z1999 | AX1999: ='Tenant Info'!AA1999 | AY1999: ='Tenant Info'!AB1999 | AZ1999: ='Tenant Info'!AC1999 | BA1999: ='Tenant Info'!AD1999 | BB1999: ='Tenant Info'!AE1999 | ... BE1999: ='Tenant Info'!AH1999 | BF1999: ='Tenant Payment info'!U1999 | BG1999: ='Tenant Payment info'!V1999 | BH1999: ='Tenant Payment info'!M1999 | BI1999: ='Tenant Payment info'!P1999 | BJ1999: ='Tenant Payment info'!W1999 | BK1999: ='Tenant Payment info'!AA1999 | BL1999: ='Tenant Payment info'!N1999 | BM1999: ='Tenant Payment info'!O1999 | BN1999: ='Tenant Payment info'!S1999 | BO1999: ='Tenant Payment info'!Q1999 | BP1999: ='Tenant Payment info'!R1999 | BQ1999: ='Tenant Payment info'!T1999 | BR1999: ='Tenant Payment info'!X1999 | BS1999: ='Tenant Payment info'!Y1999 | BT1999: ='Tenant Payment info'!Z1999 | BX1999: =PromotionsDiscounts!D1999 | BY1999: =PromotionsDiscounts!E1999 | BZ1999: =PromotionsDiscounts!F1999 | CA1999: =PromotionsDiscounts!G1999 | CB1999: =PromotionsDiscounts!H1999 | CC1999: =PromotionsDiscounts!I1999 | CD1999: =PromotionsDiscounts!J1999 | CE1999: =PromotionsDiscounts!K1999 | CF1999: ='Tenants Military Information'!F1999 | CG1999: ='Tenants Military Information'!G1999 | CH1999: ='Tenants Military Information'!H1999 | CI1999: ='Tenants Military Information'!I1999 | CJ1999: ='Tenants Military Information'!J1999 | CK1999: ='Tenants Military Information'!K1999 | CL1999: ='Tenants Military Information'!L1999 | CM1999: ='Tenants Military Information'!M1999 | ... CV1999: ='Tenants Military Information'!V1999 | CW1999: ='Tenants Lien Holder Information'!E1999 | CX1999: ='Tenants Lien Holder Information'!F1999 | CY1999: ='Tenants Lien Holder Information'!G1999 | CZ1999: ='Tenants Lien Holder Information'!H1999 | DA1999: ='Tenants Lien Holder Information'!I1999 | DB1999: ='Tenants Lien Holder Information'!J1999 | DC1999: ='Tenants Lien Holder Information'!K1999 | DD1999: ='Tenants Lien Holder Information'!L1999 | DE1999: ='Tenants Lien Holder Information'!M1999

Sheet Formulas
B2: Action | C2: MAC | D2: Windows
B3: Add Filter for Occupied Spaces Only | C3: ⌘ + Option + Shift + 1 | D3: Control + Alt + Shift +1 | E3: optional
B4: Remove Filter | C4: ⌘ + Option + Shift + 2 | D4: Control + Alt + Shift +2 | E4: optional
B5: Combine First and Last Name | C5: ⌘ + Option + Shift + 3 | D5: Control + Alt + Shift +3 | E5: required
B6: Identify Duplicates | C6: ⌘ + Option + Shift + 4 | D6: Control + Alt + Shift +4 | E6: required
B7: Remove Above Action | C7: ⌘ + Option + Shift + 5 | D7: Control + Alt + Shift +5 | E7: required
B8: Delete Concatenated Name | C8: ⌘ + Option + Shift + 6 | D8: Control + Alt + Shift +6 | E8: required

Sheet MIG Team Final Sheet
A1: Owner | B1: Name | C1: Status | D1: Space | E1: Width | F1: Length | G1: Height | H1: Rate | I1: Web_Rate | J1: Space_Size | K1: Space_Category | L1: Space_Type | M1: Door_Width | N1: Door_Height | O1: Amenities | P1: Sq_Ft | Q1: Floor | R1: First_Name | S1: Last_Name | T1: Middle_Name | U1: Account_Code | V1: Address | W1: Address2 | X1: City | Y1: State | Z1: ZIP | AA1: country | AB1: Email | AC1: Cell_Phone | AD1: Home_Phone | AE1: Work_Phone | AF1: Access_Code | AG1: DOB | AH1: Active_military | AI1: DL_ID | AJ1: DL_State | AK1: Rent | AL1: Last_Rent_Change_Date | AM1: Last_rent_amt | AN1: Scheduled_Rent_Change_Date | AO1: Scheduled_Rent | AP1: Scheduled_Rent_Notification | AQ1: Move_In_Date | AR1: Move_Out_Date | AS1: Paid_date | AT1: Bill_Day | AU1: Paid_Through_Date | AV1: Alt_First_Name | AW1: Alt_Last_Name | AX1: Alt_Middle_Name | AY1: Alt_Address | AZ1: Alt_Address2 | BA1: Alt_City | BB1: Alt_State | BC1: Alt_ZIP | BD1: Alt_Email | BE1: Alt_Home_Phone | BF1: Alt_Work_Phone | BG1: Alt_Cell_Phone | BH1: Security_Deposit | BI1: Security_Deposit_Balance | BJ1: Rent_Balance | BK1: Fees_Balance | BL1: Protection_Plan_Balance | BM1: Merchandise_Balance | BN1: Late_Fees_Balance | BO1: Tax_Balance | BP1: Prepaid_Rent | BQ1: Protection_Provider | BR1: Protection_start_date | BS1: Protection_end_date | BT1: Protection_Coverage | BU1: Additional_Rent | BV1: Promotion | BW1: Promotion_Type | BX1: Promotion_Value | BY1: Promotion_Start | BZ1: Promotion_End | CA1: Promotion_Length | CB1: Discount | CC1: Discount_Type | CD1: Discount_Value | CE1: Alarm_Enabled | CF1: Twenty_Four_Hour_Access | CG1: payment_cycle | CH1: IsBusinessLease | CI1: start_date | CJ1: company_name | CK1: company_address | CL1: company_address2 | CM1: company_city | CN1: company_state | CO1: company_zip | CP1: company_phone | CQ1: company_email
